Workbook
Name ___KK1: #REF!
Name ___LAG1: #REF!
Name ___LAG2: #REF!
Name ___LAG3: #REF!
Name ___REP1: #REF!
Name __KK1: #REF!
Name __KK1: #REF!
Name __KK1: #REF!
Name __LAG1: #REF!
Name __LAG1: #REF!
Name __LAG1: #REF!
Name __LAG2: #REF!
Name __LAG2: #REF!
Name __LAG2: #REF!
Name __LAG3: #REF!
Name __LAG3: #REF!
Name __LAG3: #REF!
Name __REP1: #REF!
Name __REP1: #REF!
Name __REP1: #REF!
Name _KK1: #REF!
Name _KK1: #REF!
Name _KK1: #REF!
Name _LAG1: #REF!
Name _LAG1: #REF!
Name _LAG1: #REF!
Name _LAG2: #REF!
Name _LAG2: #REF!
Name _LAG2: #REF!
Name _LAG3: #REF!
Name _LAG3: #REF!
Name _LAG3: #REF!
Name _REP1: #REF!
Name _REP1: #REF!
Name _REP1: #REF!
Name GENERALES: #REF!
Name GENERALES: #REF!
Name GENERALES: #REF!
Name MENU1: #REF!
Name MENU1: #REF!
Name MENU1: #REF!
Name MENUGRA: #REF!
Name MENUGRA: #REF!
Name MENUGRA: #REF!
Name MENUING: #REF!
Name MENUING: #REF!
Name MENUING: #REF!
Name MENUINGLAG: #REF!
Name MENUINGLAG: #REF!
Name MENUINGLAG: #REF!
Name MENUREP: #REF!
Name MENUREP: #REF!
Name MENUREP: #REF!
Name MENUVER: #REF!
Name MENUVER: #REF!
Name MENUVER: #REF!
Name NOMBRE: #REF!
Name NOMBRE: #REF!
Name NOMBRE: #REF!
Name NOMHEAD: #REF!

Sheet DATOS Y SISTEMA IMPULSIÓN RÍO
A1: 1- DATOS Y SISTEMA IMPULSIÓN RÍO | E1: Observaciones
A2: SISTEMA DE IMPULSIÓN | E2: Números de edificios por manzanas: suma de las cantidades de letras que poseen los primeros apellidos de los integrantes del grupo divido el número de la cantidad de integrantes
A3: Seleccionar un barrio de | B3: 12 | C3: manzanas
A4: Números de lotes/edificios por manzanas | B4: 6 | C4: lotes
A5: Números de pisos tipo | B5: 22 | C5: pisos | E5: Números de pisos por edificios: suma de las cantidades de letras que posee el primer nombre dividido 1,5, más planta baja y 1 subsuelos
A6: Números de departamentos por pisos | B6: 6 | C6: depto
A7: Números de dormitorios por departamentos | B7: 3 | C7: dorm
A8: Números de personas por dormitorios | B8: 2 | C8: pers
A9: Números de personal de servicio por departamento | B9: 1 | C9: pers
A10: Porcentaje de personal de logística por lote | B10: 10 | C10: %
A11: Total de personas de los departamentos | B11: =+B3*B4*(B5*B6*(B7*B8+B9)) -> 66528 | C11: pers
A12: Personales de logística | B12: =(B6*B5)*B10/100*B4*B3 -> 950.4 | C12: funcionarios | E12: Tabla 1
A13: Caudal unitario por persona por departamento | B13: 200 | C13: l/pers/d | D13: Norma 68 | E13: Departamentos
A14: Caudal unitario por trabajadores de logisticas | B14: 50 | C14: l/pers/d | D14: Norma 68 | E14: Oficinas
A15: Caudal medio de bombeo total | B15: =B11*B13+B12*B14 -> 13353120 | C15: l/d
B16: =+B15/1000 -> 13353.12 | C16: m3/d
B17: =+B15/86400 -> 154.55 | C17: l/s
A18: Caudal por lotes/edificios | B18: =+B15/(B3*B4) -> 185460 | C18: l/d/lotes
B19: =+B18/86400 -> 2.1465278 | C19: l/s/lotes
A20: K1 | B20: 1.2 | C20: Consumo Máx. Diario
A21: K2 | B21: 1.5 | C21: Consumo Máx. Horario
A22: K3 | B22: 1.05 | C22: Línea de impulsión
A23: Caudal de bombeo | B23: =B20*B22*B16/86400 -> 0.194733 | C23: m3/s | D23: =+B23*1000 -> 194.733 | E23: l/s
A24: Número de horas de operación de la bomba por día | B24: =(15*2*24)/60 -> 12 | C24: hs | X24: TABLA 3
X25: Diámetro Nominal | Z25: Curva 90 | AI25: Valv. de cierre | AM25: Tee lateral | AN25: Tee 2 salidas | AO25: Valv. de Pie | AQ25: Valv. de retención
A26: Diametro impulsión (fórmula de Bresse) | B26: =1.3*(B23^0.5)*(((B24/24)^(1/4))) -> 0.48239815 | C26: m | X26: DN | Y26: Ref.
A27: Diámetro adop | B27: Alt 1 | C27: Alt 2 | D27: Alt 3 | X27: mm | Y27: (“)
A28: Succión | B28: 550 | C28: 500 | D28: 350 | E28: mm | F28: El de succión debe ser un diámetro superior al de impulsión | X28: 13 | Y28: ½ | Z28: 0.3 | AA28: 0.40 | AB28: 0.5 | AC28: 0.2 | AD28: 0.2 | AE28: 0.3 | AF28: 0.2 | AG28: 0.2 | AH28: 0.4 | AI28: 0.1 | AJ28: 4.9 | AK28: 2.6 | AL28: 0.3 | AM28: 1.0 | AN28: 1.0 | AO28: 3.6 | AP28: 0.4 | AQ28: 1.1 | AR28: 1.6
A29: Impulsión | B29: 500 | C29: 450 | D29: 300 | E29: mm | X29: 19 | Y29: ¾ | Z29: 0.4 | AA29: 0.6 | AB29: 0.7 | AC29: 0.3 | AD29: 0.3 | AE29: 0.4 | AF29: 0.2 | AG29: 0.2 | AH29: 0.5 | AI29: 0.1 | AJ29: 6.7 | AK29: 3.6 | AL29: 0.4 | AM29: 1.4 | AN29: 1.4 | AO29: 5.6 | AP29: 0.5 | AQ29: 1.6 | AR29: 2.4
X30: 25 | Y30: 1 | Z30: 0.5 | AA30: 0.7 | AB30: 0.8 | AC30: 0.4 | AD30: 0.3 | AE30: 0.5 | AF30: 0.2 | AG30: 0.3 | AH30: 0.7 | AI30: 0.2 | AJ30: 8.2 | AK30: 46 | AL30: 0.5 | AM30: 1.7 | AN30: 1.7 | AO30: 7.3 | AP30: 0.7 | AQ30: 2.1 | AR30: 3.2
A31: Verificación de las velocidades: 0,7 < v < 4,0 | X31: 32 | Y31: 1 ¼ | Z31: 0.7 | AA31: 0.9 | AB31: 1.1 | AC31: 0.5 | AD31: 0.4 | AE31: 0.6 | AF31: 0.3 | AG31: 0.4 | AH31: 0.9 | AI31: 0.2 | AJ31: 11.3 | AK31: 5.6 | AL31: 0.7 | AM31: 2.3 | AN31: 2.3 | AO31: 10.0 | AP31: 0.9 | AQ31: 2.7 | AR31: 4.0
A32: Velocidad de Succión: vsucción | B32: =+B23/(PI()*((B28/1000)^2)/4) -> 0.81964217 | C32: =+B23/(PI()*((C28/1000)^2)/4) -> 0.99176703 | D32: =+B23/(PI()*((D28/1000)^2)/4) -> 2.0240143 | E32: m/s | F32: =+IF((B32>=0.7),IF(B32<=4,"Verifica","Aumentar Diametro"),"Disminuir Diametro") -> Verifica | G32: =+IF((C32>=0.7),IF(C32<=4,"Verifica","Aumentar Diametro"),"Disminuir Diametro") -> Verifica | H32: =+IF((D32>=0.7),IF(D32<=4,"Verifica","Aumentar Diametro"),"Disminuir Diametro") -> Verifica | X32: 38 | Y32: 1 ½ | Z32: 0.9 | AA32: 1.1 | AB32: 1.3 | AC32: 0.6 | AD32: 0.5 | AE32: 0.7 | AF32: 0.3 | AG32: 0.5 | AH32: 1.0 | AI32: 0.3 | AJ32: 13.4 | AK32: 6.7 | AL32: 0.9 | AM32: 2.8 | AN32: 2.8 | AO32: 11.6 | AP32: 1.0 | AQ32: 3.2 | AR32: 4.8
A33: Velocidad de impulsión: vimpulsión | B33: =+B23/(PI()*((B29/1000)^2)/4) -> 0.99176703 | C33: =+B23/(PI()*((C29/1000)^2)/4) -> 1.2244037 | D33: =+B23/(PI()*((D29/1000)^2)/4) -> 2.7549084 | E33: m/s | F33: =+IF((B33>=0.7),IF(B33<=4,"Verifica","Aumentar Diametro"),"Disminuir Diametro") -> Verifica | G33: =+IF((C33>=0.7),IF(C33<=4,"Verifica","Aumentar Diametro"),"Disminuir Diametro") -> Verifica | H33: =+IF((D33>=0.7),IF(D33<=4,"Verifica","Aumentar Diametro"),"Disminuir Diametro") -> Verifica | X33: 50 | Y33: 2 | Z33: 1.1 | AA33: 1.4 | AB33: 1.7 | AC33: 0.8 | AD33: 0.6 | AE33: 0.9 | AF33: 0.4 | AG33: 0.7 | AH33: 1.5 | AI33: 0.4 | AJ33: 17.4 | AK33: 8.5 | AL33: 1.1 | AM33: 3.5 | AN33: 3.5 | AO33: 14.0 | AP33: 1.5 | AQ33: 4.2 | AR33: 6.4
X34: 63 | Y34: 2 ½ | Z34: 1.3 | AA34: 1.7 | AB34: 2.0 | AC34: 0.9 | AD34: 0.8 | AE34: 1.0 | AF34: 0.5 | AG34: 0.9 | AH34: 1.9 | AI34: 0.4 | AJ34: 21.0 | AK34: 10.0 | AL34: 1.3 | AM34: 4.3 | AN34: 4.3 | AO34: 17.0 | AP34: 1.9 | AQ34: 5.2 | AR34: 8.1
A35: Pérdida por metro de tuberia | B35: 6.10.2.1 Fórmulas de Fair Whipple – Hsiao para Acero Galvanizado | X35: 75 | Y35: 3 | Z35: 1.6 | AA35: 2.1 | AB35: 2.5 | AC35: 1.2 | AD35: 1.0 | AE35: 1.3 | AF35: 0.6 | AG35: 1.1 | AH35: 2.2 | AI35: 0.5 | AJ35: 26.0 | AK35: 13.0 | AL35: 1.6 | AM35: 5.2 | AN35: 5.2 | AO35: 20.0 | AP35: 2.2 | AQ35: 6.3 | AR35: 9.7
A36: J succion | B36: =+(B23/((27.113*(B28/1000)^2.596)))^(1/0.532) -> 0.0017273059 | C36: =+(B23/((27.113*(C28/1000)^2.596)))^(1/0.532) -> 0.0027501292 | D36: =+(B23/((27.113*(D28/1000)^2.596)))^(1/0.532) -> 0.015675741 | E36: m/m | X36: 100 | Y36: 4 | Z36: 2.1 | AA36: 2.8 | AB36: 3.4 | AC36: 1.5 | AD36: 1.3 | AE36: 1.6 | AF36: 0.7 | AG36: 1.6 | AH36: 3.2 | AI36: 0.7 | AJ36: 34.0 | AK36: 17.0 | AL36: 2.1 | AM36: 6.7 | AN36: 6.7 | AO36: 23.0 | AP36: 3.2 | AQ36: 6.4 | AR36: 12.9
A37: J impulsión | B37: =+(B23/((27.113*(B29/1000)^2.596)))^(1/0.532) -> 0.0027501292 | C37: =+(B23/((27.113*(C29/1000)^2.596)))^(1/0.532) -> 0.0045987086 | D37: =+(B23/((27.113*(D29/1000)^2.596)))^(1/0.532) -> 0.03325893 | E37: m/m | X37: 125 | Y37: 5 | Z37: 2.7 | AA37: 3.7 | AB37: 4.2 | AC37: 1.9 | AD37: 1.6 | AE37: 2.1 | AF37: 0.9 | AG37: 2.0 | AH37: 4.0 | AI37: 0.9 | AJ37: 43.0 | AK37: 21.0 | AL37: 2.7 | AM37: 8.4 | AN37: 8.4 | AO37: 30.0 | AP37: 4.0 | AQ37: 10.4 | AR37: 16.1
X38: 150 | Y38: 6 | Z38: 3.4 | AA38: 4.3 | AB38: 4.9 | AC38: 2.3 | AD38: 1.9 | AE38: 2.5 | AF38: 1.1 | AG38: 2.5 | AH38: 5.0 | AI38: 1.1 | AJ38: 51.0 | AK38: 26.0 | AL38: 3.4 | AM38: 10.0 | AN38: 10.0 | AO38: 39.0 | AP38: 5.0 | AQ38: 12.5 | AR38: 19.3
A39: Pérdidas localizadas | X39: 200 | Y39: 8 | Z39: 4.3 | AA39: 5.5 | AB39: 6.4 | AC39: 3.0 | AD39: 2.4 | AE39: 3.3 | AF39: 1.5 | AG39: 3.5 | AH39: 6.0 | AI39: 1.4 | AJ39: 67.0 | AK39: 34.0 | AL39: 4.3 | AM39: 13.0 | AN39: 13.0 | AO39: 52.0 | AP39: 6.0 | AQ39: 16.0 | AR39: 25.0
A40: Succión | B40: =L50 -> 129.7 | C40: =M50 -> 112.1 | D40: =N50 -> 129 | E40: m.c.a. | F40: Ver ANEXO I al III de la NORMA 68 | X40: 250 | Y40: 10 | Z40: 5.5 | AA40: 6.7 | AB40: 7.9 | AC40: 3.8 | AD40: 3.0 | AE40: 4.1 | AF40: 1.8 | AG40: 4.5 | AH40: 7.5 | AI40: 1.7 | AJ40: 85.0 | AK40: 43.0 | AL40: 5.5 | AM40: 16.0 | AN40: 16.0 | AO40: 65.0 | AP40: 7.5 | AQ40: 20.0 | AR40: 32.0
A41: Impulsión | B41: =L56 -> 51.9 | C41: =M56 -> 43 | D41: =N56 -> 51.3 | E41: m.c.a. | F41: Ver ANEXO I al III de la NORMA 68 | X41: 300 | Y41: 11 | Z41: 6.1 | AA41: 7.9 | AB41: 9.5 | AC41: 4.6 | AD41: 3.6 | AE41: 4.8 | AF41: 2.2 | AG41: 5.5 | AH41: 9.0 | AI41: 2.2 | AJ41: 102.0 | AK41: 51.0 | AL41: 6.1 | AM41: 19.0 | AN41: 19.0 | AO41: 78.0 | AP41: 9.0 | AQ41: 24.0 | AR41: 38.0
X42: 350 | Y42: 12 | Z42: 7.3 | AA42: 9.5 | AB42: 10.5 | AC42: 5.3 | AD42: 4.4 | AE42: 5.4 | AF42: 2.5 | AG42: 6.2 | AH42: 11.0 | AI42: 2.4 | AJ42: 120.0 | AK42: 60.0 | AL42: 7.3 | AM42: 22.0 | AN42: 22.0 | AO42: 90.0 | AP42: 11.0 | AQ42: 28.0 | AR42: 45.0
A43: Longitud de tubería | K43: Perdidas Localizadas | L43: Anexo, tabla 3 de norma 68 | X43: 400 | Y43: 13.5 | Z43: 4.4 | AA43: 5.6 | AB43: 6.5 | AC43: 3.16 | AD43: 2.5 | AE43: 3.4 | AF43: 1.11 | AG43: 3.6 | AH43: 6.1 | AI43: 1.10 | AJ43: 67.1 | AK43: 34.1 | AL43: 4.4 | AM43: 13.0 | AN43: 13.0 | AO43: 52.1 | AP43: 6.1 | AQ43: 16.1 | AR43: 25.1
A44: Succión | B44: 2 | C44: =+B44 -> 2 | D44: =+B44 -> 2 | E44: m | K44: Succión | L44: =+B28 -> 550 | M44: =+C28 -> 500 | N44: =+D28 -> 350 | X44: 450 | Y44: 14.8 | Z44: 5.6 | AA44: 6.8 | AB44: 7.10 | AC44: 3.24 | AD44: 3.12 | AE44: 4.15 | AF44: 1.14 | AG44: 4.6 | AH44: 7.6 | AI44: 1.13 | AJ44: 85.1 | AK44: 43.1 | AL44: 5.6 | AM44: 16.0 | AN44: 16.0 | AO44: 65.1 | AP44: 7.6 | AQ44: 20.1 | AR44: 32.1
A45: Impulsión | B45: 669.35 | C45: =+B45 -> 669.35 | D45: =+C45 -> 669.35 | E45: m | K45: Val. De Pie | L45: 90.1 | M45: 78.1 | N45: 90 | O45: Tabla 3, la cuarta desde la derecha | X45: 500 | Y45: 16.1 | Z45: 6.2 | AA45: 7.10 | AB45: 9.6 | AC45: 4.7 | AD45: 3.18 | AE45: 4.22 | AF45: 2.8 | AG45: 5.6 | AH45: 9.1 | AI45: 2.6 | AJ45: 102.1 | AK45: 51.1 | AL45: 6.2 | AM45: 19.0 | AN45: 19.0 | AO45: 78.1 | AP45: 9.1 | AQ45: 24.1 | AR45: 38.1
K46: Curva 90 | L46: 7.4 | M46: 6.2 | N46: 7.3 | O46: Tabla 3, la 1ra desde la izquierda | X46: 550 | Y46: 17.4 | Z46: 7.4 | AA46: 9.6 | AB46: 10.6 | AC46: 5.4 | AD46: 4.5 | AE46: 5.5 | AF46: 2.11 | AG46: 6.3 | AH46: 11.1 | AI46: 2.8 | AJ46: 120.1 | AK46: 60.1 | AL46: 7.4 | AM46: 22.0 | AN46: 22.0 | AO46: 90.1 | AP46: 11.1 | AQ46: 28.1 | AR46: 45.1
A47: Altura topográfica | K47: Tee 2salida | L47: 22 | M47: 19 | N47: 22 | O47: Tabla 3, 5ta a la derecha
A48: Succión | B48: 2 | C48: =+B48 -> 2 | D48: =+B48 -> 2 | E48: m | K48: Curva 90 | L48: 7.4 | M48: 6.2 | N48: 7.3
A49: Impulsión | B49: =75-70+4 -> 9 | C49: =+B49 -> 9 | D49: =+B49 -> 9 | E49: m | K49: Valv. De Cierre | L49: 2.8 | M49: 2.6 | N49: 2.4 | O49: El dibujo mas grande, globo
K50: Total: | L50: =SUM(L45:L49) -> 129.7 | M50: =SUM(M45:M49) -> 112.1 | N50: =SUM(N45:N49) -> 129
A51: Velocidad en la tubería | K51: Impulsión | L51: =+B29 -> 500 | M51: =+C29 -> 450 | N51: =+D29 -> 300
A52: Succión | B52: =+B23/(PI()*((B28/1000)^2)/4) -> 0.81964217 | C52: =+B23/(PI()*((C28/1000)^2)/4) -> 0.99176703 | D52: =+B23/(PI()*((D28/1000)^2)/4) -> 2.0240143 | E52: m/s | F52: =+IF((B52<=0.5), "Disminuir Diametro", "Verifica") -> Verifica | G52: =+IF((D52<=0.5), "Disminuir Diametro", "Verifica") -> Verifica | K52: Curva 90 | L52: 6.2 | M52: 5.6 | N52: 6.1
A53: Impulsión | B53: =+B23/(PI()*((B29/1000)^2)/4) -> 0.99176703 | C53: =+B23/(PI()*((C29/1000)^2)/4) -> 1.2244037 | D53: =+B23/(PI()*((D29/1000)^2)/4) -> 2.7549084 | E53: m/s | F53: =+IF((B53<=0.5), "Disminuir Diametro", "Verifica") -> Verifica | G53: =+IF((D53<=0.5), "Disminuir Diametro", "Verifica") -> Verifica | K53: Valv. De Retenc | L53: 24.1 | M53: 20.1 | N53: 24 | O53: 2do de la derecha
K54: Valv. De Cierre | L54: 2.6 | M54: 1.3 | N54: 2.2
A55: Presión de llegada al reservorio | B55: 0.5 | C55: =+B55 -> 0.5 | D55: =+C55 -> 0.5 | E55: m | F55: Esto sería un factor de seguridad | K55: Tee lateral | L55: 19 | M55: 16 | N55: 19 | O55: 6to de la derecha
K56: Total: | L56: =SUM(L52:L55) -> 51.9 | M56: =SUM(M52:M55) -> 43 | N56: =SUM(N52:N55) -> 51.3
A57: Altura Manométrica o Gradiente Hidraúlico
A58: Succión | B58: =+B48+(B44+B40)*B36+((B52^2)/(2*9.8)) -> 2.2617624 | C58: =+C48+(C44+C40)*C36+((C52^2)/(2*9.8)) -> 2.3639735 | D58: =+D48+(D44+D40)*D36+((D52^2)/(2*9.8)) -> 4.262534 | E58: m.c.a.
A59: Impulsión | B59: =+B49+(B45+B41)*B37+((B53^2)/(2*9.8)) -> 11.033714 | C59: =+C49+(C45+C41)*C37+((C53^2)/(2*9.8)) -> 12.352378 | D59: =+D49+(D45+D41)*D37+((D53^2)/(2*9.8)) -> 33.355269 | E59: m.c.a.
A60: Total | B60: =+B59+B58+B55 -> 13.795477 | C60: =+C59+C58+C55 -> 15.216352 | D60: =+D59+D58+D55 -> 38.117803 | E60: m.c.a.
M61: TABLA 6: Rendimiento para bombas centrifugas
M62: Q (l/s) | N62: 2.5 | O62: 5 | P62: 7.5 | Q62: 10 | R62: 15 | S62: 20 | T62: 25 | U62: 30 | V62: 40 | W62: 50 | X62: 100 | Y62: 200
A63: Potencia de la Bomba | M63: hb [%] | N63: 45 | O63: 52 | P63: 61 | Q63: 66 | R63: 68 | S63: 71 | T63: 75 | U63: 80 | V63: 84 | W63: 85 | X63: 87 | Y63: 88
A64: Pb | B64: =1000*B60*B23/75/H65 -> 40.703554 | C64: =1000*C60*B23/75/I65 -> 44.895845 | D64: =1000*D60*B23/75/J65 -> 112.46658 | E64: cv
B65: =1.014*B64 -> 41.273404 | C65: =1.014*C64 -> 45.524387 | D65: =1.014*D64 -> 114.04111 | E65: HP | F65: =D23 -> 194.733 | G65: ∩bomba | H65: 0.88 | I65: =+H65 -> 0.88 | J65: =+I65 -> 0.88 | K65: VER TABLA 6 y 7 NORMA 68 | M65: TABLA 7: Rendimiento de motores eléctricos
A66: Pmb | B66: =+B65/H66 -> 46.901596 | C66: =+C65/I66 -> 51.732258 | D66: =+D65/J66 -> 126.71234 | E66: HP | G66: ∩motor | H66: 0.88 | I66: 0.88 | J66: 0.9 | M66: HP | N66: ¼ | P66: ½ | Q66: ¾ | R66: 1 | S66: 1½ | T66: 2 | U66: 3 | V66: 4 | W66: 5 | X66: 6 | Y66: 7½ | Z66: 10 | AA66: 12 | AB66: 15 | AC66: 20 | AD66: 30 | AE66: 50 | AF66: 100
A67: Holgura (de acuerdo al Pmb) | B67: 10 | C67: 10 | D67: 10 | E67: % | M67: hm [%] | N67: 61 | O67: 63 | P67: 64 | Q67: 67 | R67: 72 | S67: 73 | T67: 75 | U67: 77 | V67: 79 | W67: 81 | X67: 82 | Y67: 82.4 | Z67: 83 | AA67: 84 | AB67: 85 | AC67: 86 | AD67: 87 | AE67: 88 | AF67: 90
A68: Phmb | B68: =(1+B67/100)*B66 -> 51.591755 | C68: =(1+C67/100)*C66 -> 56.905484 | D68: =(1+D67/100)*D66 -> 139.38358 | E68: HP
A69: Padop | C69: 60 | D69: HP | G69: VER TABLA 8 de la NORMA 68
G70: Holgura Tipo de bomba 50% Para bombas de hasta 2 HP 30% Para bombas de 2 a 5 HP 20% Para bombas de 5 a 10 HP 15% Para bombas de 10 a 20 HP 10% Para bombas de más de 20 HP
A71: Pozo de bombeo
A72: Altura minima del agua sobre la criba
A73: Por cavitación = | B73: =+((B52^2)/(2*9.8))+0.2 -> 0.23427619 | C73: =+((C52^2)/(2*9.8))+0.2 -> 0.25018377 | D73: =+((D52^2)/(2*9.8))+0.2 -> 0.40901194 | E73: m
A74: Por serguridad > | B74: 0.5 | E74: m
A75: Adopta el mayor | B75: 0.5 | E75: m
A77: Selección del diámetro del mínimo costo
A78: Se debe escogen tres (3) diámetros comerciales en torno al valor de Bresse, para poder seleccionar el diámetro más adecuado
A79: Se realiza un análisis de costos que involucra: | E79: Costo
A80: • costos de tuberías | D80: Inversión | E80: $tuberia | F80: y bomba
A81: • costos de los equipos de bombeo | D81: Operación | E81: $ potencia | F81: mantenimiento
A82: • costos de operación y mantenimiento | D82: Vida Útil | E82: Bomba 7 años | F82: Tuberia 50 años

Sheet POTABILIZADORA
A1: 2- POTABILIZADORA
A2: Caudal diario | B2: =+'DATOS Y SISTEMA IMPULSIÓN RÍO'!B16 -> 13353.12 | C2: m3/d | D2: De hoja de datos
A3: Caudal de captación: Qcap
A4: K1 = | B4: =+'DATOS Y SISTEMA IMPULSIÓN RÍO'!B20 -> 1.2
A5: K2 = | B5: =+'DATOS Y SISTEMA IMPULSIÓN RÍO'!B21 -> 1.5
A6: K3 = | B6: =+'DATOS Y SISTEMA IMPULSIÓN RÍO'!B22 -> 1.05
A7: Qcap = | B7: =+B2*B4*B6*1000/86400 -> 194.733 | C7: l/s
D8: Q = v*A
A9: Cámara de aquietamiento | D9: A = Q/v | G9: Parshall | I9: "V"
A10: Velocidad ascencional (4 a 10) = | B10: 8.6 | C10: cm/s
A11: Area de la sección trasversal = | B11: =+(B7/1000)/(B10/100) -> 2.2643372 | C11: m2 | D11: 0.285 | G11: =+G12+D11 -> 0.72334026 | H11: = E | I11: =+H12+D11 -> 2.1498 | J11: = E
A12: Lados del aquietador = | B12: =+B11^0.5 -> 1.5047715 | C12: m | G12: =+B26 -> 0.43834026 | H12: =+H57+H52 -> 1.8648
C13: =D14+D11 -> 3.0026
A14: Tiempo de aquietamiento (30 a 60) = | B14: 31.6 | C14: s | D14: =+B15 -> 2.7176
A15: Profundidad de la cámara de aquietamiento = | B15: =((B7/1000)*(B14))/B11 -> 2.7176 | C15: m
E18: =+F20 -> 1.5047715
F20: =+B12 -> 1.5047715
A24: Canal aforador parshall y su uso como posible mezclador rápido
A25: Ancho de la garganta: W = | B25: 0.305 | C25: m | D25: =B25/2 -> 0.1525 | L25: Garganta: W | N25: Caudal (l/s) | P25: =B7 -> 194.733
A26: Altura del agua a la llegada: H = | B26: =+((B7/1000)/(2.2*B25))^(0.666666666666667) -> 0.43834026 | C26: m | E26: =0.6+0.159 -> 0.759 | L26: Pulg / pies | M26: m | N26: Minima | O26: Maxima | P26: Medio
A27: Altura del escalón del resalto: N = | B27: 0.229 | C27: m | D27: =0.298-0.21 -> 0.088 | L27: 1'' | M27: 0.025
A28: Diferencia entre el piso de llegada y salida: K = | B28: 0.076 | C28: m | L28: 3" | M28: 0.076 | N28: 0.85 | O28: 53.8 | P28: =AVERAGE(N28:O28) -> 27.325
A29: Altura del agua al final de la garganta: h2 = | B29: =0.6*B26 -> 0.26300415 | C29: m | D29: =B26-B30 -> 0.13150208 | E29: =D29+B28 -> 0.20750208 | H29: Parshall | L29: 6" | M29: 0.152 | N29: 1.52 | O29: 110.4 | P29: =AVERAGE(N29:O29) -> 55.96
A30: Altura del agua a la salida: H3 = | B30: =0.7*B26 -> 0.30683818 | C30: m | L30: 9" | M30: 0.229 | N30: 2.55 | O30: 251.9 | P30: =AVERAGE(N30:O30) -> 127.225 | X30: =25.9/100 -> 0.259
A31: Perdida de carga: h1 = | B31: =+B26-B30-B28 -> 0.055502077 | C31: m | L31: 1' | M31: 0.305 | N31: 3.11 | O31: 455.6 | P31: =AVERAGE(N31:O31) -> 229.355
A32: Verificación de velocidad: 2 ≤ | B32: =+B7/1000/(B25*B29) -> 2.4275999 | C32: m/s | D32: =+IF(B32<=2,"No sirve como Mezclador Rápidos","Se pueda usar como Mezclador Rápido") -> Se pueda usar como Mezclador Rápido | H32: =+B25 -> 0.305 | L32: 1 1/2' | M32: 0.457 | N32: 4.25 | O32: 696.2 | P32: =AVERAGE(N32:O32) -> 350.225 | X32: =45.7/100 -> 0.457
A33: A = | B33: 1.372 | C33: m | L33: 2' | M33: 0.61 | N33: 11.89 | O33: 936.7 | P33: =AVERAGE(N33:O33) -> 474.295
A34: 2/3 A = | B34: =2/3*B33 -> 0.91466667 | C34: m | L34: 3' | M34: 0.915 | N34: 17.26 | O34: 1426.3 | P34: =AVERAGE(N34:O34) -> 721.78
L35: 4' | M35: 1.22 | N35: 36.79 | O35: 1921.5 | P35: =AVERAGE(N35:O35) -> 979.145 | X35: =15.2/100 -> 0.152
F36: =+G11 -> 0.72334026 | H36: =+B26 -> 0.43834026 | L36: 5' | M36: 1.525 | N36: 62.8 | O36: 2422 | P36: =AVERAGE(N36:O36) -> 1242.4
A37: Vertedero "V" | D37: En caso de que no verifique Parshall | J37: =+B28 -> 0.076 | L37: 6' | M37: 1.83 | N37: 74.4 | O37: 2929 | P37: =AVERAGE(N37:O37) -> 1501.7
A38: DATOS | H38: =+B27 -> 0.229 | I38: =+B30 -> 0.30683818 | L38: 7' | M38: 2.135 | N38: 115.4 | O38: 3440 | P38: =AVERAGE(N38:O38) -> 1777.7 | X38: =0.178/2 -> 0.089
A39: Q | B39: =B40/1000 -> 0.194733 | C39: m3/s | H39: =+B29 -> 0.26300415 | L39: 8' | M39: 2.44 | N39: 130.7 | O39: 3950 | P39: =AVERAGE(N39:O39) -> 2040.35
A40: Qcap = | B40: =B7 -> 194.733 | C40: l/s | L40: 10' | M40: 3.05 | N40: 200 | O40: 5660 | P40: =AVERAGE(N40:O40) -> 2930
A41: Cd= | B41: 0.6
A42: phi = | B42: 90 | C42: grados
A43: g= | B43: 9.81 | C43: m/s2
A45: CALCULAMOS LA ALTURA MÁXIMA e QUE ES LA ALTURA DE LA LÁMINA DE AGUA EN EL VERTEDERO
A46: Hmax= | B46: =ROUNDUP((B39/((8/15)*B41*((2*9.81)^(1/2))*E46))^(2/5),4) -> 0.3728 | C46: m | D46: tang | E46: =TAN(B42/2) -> 1.6197752
A47: Hadoptado para el triangulo | B47: 0.3
A48: 2Hmax (B)= | B48: =B46*2 -> 0.7456 | C48: m
A49: 2Hmax adoptado | B49: 0.3 | C49: m | H49: =2*B49 -> 0.6
A50: >2Hmax= | B50: =B48 -> 0.7456 | C50: m
A51: altura del piso interior? | B51: =ROUNDUP(B50+B48,3) -> 1.492 | C51: m | F51: =+B49 -> 0.3
A52: altura de las paredes exteriores | B52: 0.2 | C52: m | H52: =+B46 -> 0.3728 | I52: =+B47 -> 0.3
A53: ancho del piso | B53: =ROUNDUP(2*B49+B47*2,2) -> 1.2 | C53: m
A54: 2. CAUDAL UNITARIO | B54: q= | C54: =ROUNDUP((B39/B48),4) -> 0.2612 | D54: m3/s*m | E54: m2/s
A55: 3. ALTURA CRÍTICA | B55: hc= | C55: =(((C54)^2)/B43)^(1/3) -> 0.19087942 | J55: =+H57+H52 -> 1.8648 | K55: =E
A56: 4. PROFUNDIDAD DESPUES DEL VERTEDERO h1 | B56: h1= | C56: =((C55)*((2)^(1/2)))/(1.06+(((B46/C55)+1.5)^(1/2))) -> 0.092502341 | D56: m
A57: 5. VELOCIDAD AL INICIO DEL RESALTO | B57: V1= | C57: =C54/C56 -> 2.8237123 | D57: m/s | H57: =+B51 -> 1.492
A58: 6. NUMERO DE FROUDE | B58: F= | C58: =ROUNDDOWN(C57/((B43*C56)^(1/2)),2) -> 2.96
A59: 7. ALTURA DESPUÉS DEL RESALTO | B59: h2= | C59: =(C56/2)*(1+8*(C58)^2)^(1/2) -> 0.3899739
A60: 8. VELOCIDAD AL FINAL DEL RESALTO | B60: V2= | C60: =ROUNDUP(C54/C59,4) -> 0.6698 | D60: m/s
A61: 9. ENERGIA DISIPADA EN EL RESALTO | B61: hp= | C61: =((C59-C56)^(3))/(4*C56*C59) -> 0.18242656 | H61: =+B53 -> 1.2
A62: 10. LONGITUD DEL RESALTO | B62: Lm= | C62: =6*(C59-C56) -> 1.7848293 | D62: m
A63: 11. DISTANCIA DEL VERTEDERO A LA SECCIÓN ESTABLE | B63: Lj= | C63: =(4.3*B50)*((C55/B50)^(0.9)) -> 0.94059409 | D63: m
A64: 12. VELOCIDAD PROMEDIO EN EL RESALTO | B64: Vm= | C64: =(C57+C60)/2 -> 1.7467562 | D64: m/s
A65: 13. TIEMPO DE MEZCLA | B65: T= | C65: =C62/C64 -> 1.0217965 | D65: s
A66: 14. CÁLCULO DEL GRADIENTE DE VELOCIDAD G
A67: Peso específico del agua= | B67: 1000 | C67: kgf/m3
A68: Viscocidad cinemática= | B68: =B104 -> 9.4218143e-07 | C68: m2/s
A69: Viscocidad absoluta o dinámica= | B69: =B68*B67 -> 0.00094218143 | C69: kg/m.s
A70: Factor de forma de las paletas K= | B70: 2.3 | C70: (adimensional, varía de 2 a 7)
A71: Revoluciones por segundo = | B71: =105/60 -> 1.75 | C71: rps
A72: Diametro de las paletas= | B72: =B99 -> 0.83879823 | C72: m
A73: Volumen del mezclador= | B73: =B91 -> 2500 | C73: m3
A75: Gradiente de mezcla rápida (Gr)= | B75: =((B70*B67*(B71^3)*(B72^5))/(B69*B73))^(1/2) -> 46.615193 | C75: s-1
A76: Gradiente del vertedor en V (G)= | B76: =((B67*C61)/(B69*C65))^(1/2) -> 435.30591 | C76: s-1 | D76: VERIFICA! | E76: Tiene que verificar acá para poder usar como mezclador rápido
A78: OBS: El gradiente calculado G supera al gradiente mínimo Gr, por lo tanto se garantiza una correcta mezcla entre el agua y el coagulante
A80: 15. DISEÑO DEL CANAL DE ESTABILIZACIÓN
A81: Tiempo de retención (t)= | B81: 10 | C81: segundos
A82: Velocidad fin del resalto= | B82: =C60 -> 0.6698 | C82: m/s
A83: Longitud del canal= | B83: =B81*B82 -> 6.698 | C83: m
A86: Mezclador rápidos para coagulantes | D86: En caso de no verificar vertedero en V
A87: Caudal de proyecto = | B87: =+B7*3.6 -> 701.0388 | C87: m³ /h
A88: Tiempo de retención (1 a 3) min a 105 rpm = | B88: 2.35 | C88: min
A89: Volumen del tanque = | B89: =ROUNDUP(B87*B88/60,2) -> 27.46 | C89: m³
B90: =+B89*1000 -> 27460 | C90: L
A91: Volumen adoptado = | B91: 2500 | C91: L | J91: =+B93 -> 1.1982832
A92: Altura del tanque = | B92: 1.85 | C92: m
A93: Diámetro = | B93: =((((B91/1000)/B92)*4)/PI())^(1/3) -> 1.1982832 | C93: m
A94: Eficiencia del motor y compresor (0,6 a 0,8) = | B94: 0.7
A95: Coeficiente de seguridad (1,4 a 1,5) = | B95: 1.45
A96: Potencia del mezclador = | B96: =B95*(0.0001029*(B91/1000)*1000^2/76)/B94 -> 7.0115132 | C96: HP
A97: Potencia del mezclador adoptado = | B97: 7.5 | C97: HP
A98: Longitud del brazo del mezclador = | B98: =0.666666666666667*B92 -> 1.2333333 | C98: m | I98: =+B98 -> 1.2333333 | J98: =+B92 -> 1.85
A99: Diametro de la paleta mezcladora= | B99: =B93*0.7 -> 0.83879823
I100: =+B93 -> 1.1982832
A102: Floculador o mezclador lento
A103: Temperatura = | B103: 23 | C103: ºC
A104: Viscocidad cinemática: ϑ = | B104: =0.00000131*(33.3/(B103+23.3)) -> 9.4218143e-07 | C104: m2/s | D104: Depende de la temperatura
A105: Periodo de retención: t=30 min = | B105: =0.5*3600 -> 1800 | C105: s
A106: Profundidad: h = | B106: 1.7 | C106: m | D106: tanteo
A107: Velocidad en los canales: (0,15 a 0,20); v1 = | B107: 0.175 | C107: m/s | D107: tanteo buscando redondeo de la separación de canales: b
A108: Velocidad en los pasos o vueltas: (0,40 a 0,45); v2 = | B108: 0.425 | C108: m/s | D108: Para que todas las partículas trabajen en forma similar
A109: Separación de los canales: b = Q / (v1 x h) = | B109: =+(B7/1000)/(B107*B106) -> 0.65456471 | C109: m
A110: Separación de los canales adoptado: b = | B110: 0.7 | C110: m | D110: Se adopta un valor constructivamente práctico
A111: Recalcular (0,15 a 0,20): v1 = | B111: =+(B7/1000)/(B110*B106) -> 0.16364118 | C111: m/s
A112: Ancho del paso de los bafles para v2: b' = | B112: =+(B7/1000)/(B108*B106)*0+B110*1.5*1 -> 1.05 | C112: m
A113: Volumen de retención de t=30 min: V = | B113: =+(B7/1000)*B105 -> 350.5194 | C113: m3
...

Sheet SISTEMA DE IMPULSIÓN AL TANQUE
A1: 3- SISTEMA DE IMPULSIÓN AL TANQUE
A2: Caudal medio | B2: =+POTABILIZADORA!B2 -> 13353.12 | C2: m3/d
A3: Cota de la base de la motobomba | B3: 97 | C3: msnm | D3: Depende del proyecto
A4: Cota de la base de la base del tanque elevado | B4: =+Presiones!I16 -> 97 | C4: msnm
A6: K1 | B6: =+'DATOS Y SISTEMA IMPULSIÓN RÍO'!B20 -> 1.2
A7: Caudal de bombeo | B7: =B6*B2/86400 -> 0.18546 | C7: m3/s | D7: =+B7*1000 -> 185.46 | E7: l/s
A8: Número de horas de operación de la bomba por dia | B8: 12 | C8: hs
A10: Diametro impulsión (fórmula de Bresse) | B10: =1.3*(B7^0.5)*(((B8/24)^(1/4))) -> 0.47077239 | C10: m
A11: Diametro adop | B11: Alt 1 | C11: Alt 2 | D11: Alt 3
A12: Succion | B12: 550 | C12: 500 | D12: 350 | E12: mm
A13: Impulsion | B13: 500 | C13: 450 | D13: 300 | E13: mm
A15: Verificación de las velocidades: 0,6 < v < 3,5
A16: Velocidad de succión: vsucción | B16: =+B7/(PI()*((B12/1000)^2)/4) -> 0.78061159 | C16: =+B7/(PI()*((C12/1000)^2)/4) -> 0.94454002 | D16: =+B7/(PI()*((D12/1000)^2)/4) -> 1.9276327 | E16: m/s | F16: =+IF((B16>=0.7),IF(B16<=4,"Verifica","Aumentar Diametro"),"Disminuir Diametro") -> Verifica | G16: =+IF((C16>=0.7),IF(C16<=4,"Verifica","Aumentar Diametro"),"Disminuir Diametro") -> Verifica | H16: =+IF((D16>=0.7),IF(D16<=4,"Verifica","Aumentar Diametro"),"Disminuir Diametro") -> Verifica
A17: Velocidad de impulsión: vimpulsión | B17: =+B7/(PI()*((B13/1000)^2)/4) -> 0.94454002 | C17: =+B7/(PI()*((C13/1000)^2)/4) -> 1.1660988 | D17: =+B7/(PI()*((D13/1000)^2)/4) -> 2.6237223 | E17: m/s | F17: =+IF((B17>=0.7),IF(B17<=4,"Verifica","Aumentar Diametro"),"Disminuir Diametro") -> Verifica | G17: =+IF((C17>=0.7),IF(C17<=4,"Verifica","Aumentar Diametro"),"Disminuir Diametro") -> Verifica | H17: =+IF((D17>=0.7),IF(D17<=4,"Verifica","Aumentar Diametro"),"Disminuir Diametro") -> Verifica | T17: TABLA 3
T18: Diámetro Nominal | V18: Curva 90 | AE18: Valv. de cierre | AI18: Tee lateral | AJ18: Tee 2 salidas | AK18: Valv. de Pie | AM18: Valv. de retención
A19: Pérdida por metro de tuberia | B19: 6.10.2.1 Fórmulas de Fair Whipple – Hsiao para Acero Galvanizado | T19: DN | U19: Ref.
A20: J succion | B20: =+(B7/((27.113*(B12/1000)^2.596)))^(1/0.532) -> 0.0015759402 | C20: =+(B7/((27.113*(C12/1000)^2.596)))^(1/0.532) -> 0.0025091325 | D20: =+(B7/((27.113*(D12/1000)^2.596)))^(1/0.532) -> 0.014302059 | E20: m/m | T20: mm | U20: (“)
A21: J impulsión | B21: =+(B7/((27.113*(B13/1000)^2.596)))^(1/0.532) -> 0.0025091325 | C21: =+(B7/((27.113*(C13/1000)^2.596)))^(1/0.532) -> 0.0041957189 | D21: =+(B7/((27.113*(D13/1000)^2.596)))^(1/0.532) -> 0.030344415 | E21: m/m | T21: 13 | U21: ½ | V21: 0.3 | W21: 0.40 | X21: 0.5 | Y21: 0.2 | Z21: 0.2 | AA21: 0.3 | AB21: 0.2 | AC21: 0.2 | AD21: 0.4 | AE21: 0.1 | AF21: 4.9 | AG21: 2.6 | AH21: 0.3 | AI21: 1.0 | AJ21: 1.0 | AK21: 3.6 | AL21: 0.4 | AM21: 1.1 | AN21: 1.6
T22: 19 | U22: ¾ | V22: 0.4 | W22: 0.6 | X22: 0.7 | Y22: 0.3 | Z22: 0.3 | AA22: 0.4 | AB22: 0.2 | AC22: 0.2 | AD22: 0.5 | AE22: 0.1 | AF22: 6.7 | AG22: 3.6 | AH22: 0.4 | AI22: 1.4 | AJ22: 1.4 | AK22: 5.6 | AL22: 0.5 | AM22: 1.6 | AN22: 2.4
A23: Pérdidas localizadas | T23: 25 | U23: 1 | V23: 0.5 | W23: 0.7 | X23: 0.8 | Y23: 0.4 | Z23: 0.3 | AA23: 0.5 | AB23: 0.2 | AC23: 0.3 | AD23: 0.7 | AE23: 0.2 | AF23: 8.2 | AG23: 46 | AH23: 0.5 | AI23: 1.7 | AJ23: 1.7 | AK23: 7.3 | AL23: 0.7 | AM23: 2.1 | AN23: 3.2
A24: Succión | B24: =+K31 -> 129.7 | C24: =+L31 -> 112.1 | D24: =+M31 -> 129 | E24: m.c.a. | J24: Pérdidas Localizadas | K24: Anexo, tabla 3 de norma 68 | T24: 32 | U24: 1 ¼ | V24: 0.7 | W24: 0.9 | X24: 1.1 | Y24: 0.5 | Z24: 0.4 | AA24: 0.6 | AB24: 0.3 | AC24: 0.4 | AD24: 0.9 | AE24: 0.2 | AF24: 11.3 | AG24: 5.6 | AH24: 0.7 | AI24: 2.3 | AJ24: 2.3 | AK24: 10.0 | AL24: 0.9 | AM24: 2.7 | AN24: 4.0
A25: Impulsión | B25: =+K37 -> 51.9 | C25: =+L37 -> 43 | D25: =+M37 -> 51.3 | E25: m.c.a. | J25: Succión | K25: =+B12 -> 550 | L25: =+C12 -> 500 | M25: =+D12 -> 350 | T25: 38 | U25: 1 ½ | V25: 0.9 | W25: 1.1 | X25: 1.3 | Y25: 0.6 | Z25: 0.5 | AA25: 0.7 | AB25: 0.3 | AC25: 0.5 | AD25: 1.0 | AE25: 0.3 | AF25: 13.4 | AG25: 6.7 | AH25: 0.9 | AI25: 2.8 | AJ25: 2.8 | AK25: 11.6 | AL25: 1.0 | AM25: 3.2 | AN25: 4.8
J26: Val. De Pie | K26: 90.1 | L26: 78.1 | M26: 90 | N26: Tabla 3, la cuarta desde la derecha | T26: 50 | U26: 2 | V26: 1.1 | W26: 1.4 | X26: 1.7 | Y26: 0.8 | Z26: 0.6 | AA26: 0.9 | AB26: 0.4 | AC26: 0.7 | AD26: 1.5 | AE26: 0.4 | AF26: 17.4 | AG26: 8.5 | AH26: 1.1 | AI26: 3.5 | AJ26: 3.5 | AK26: 14.0 | AL26: 1.5 | AM26: 4.2 | AN26: 6.4
A27: Longitud de tubería | J27: Curva 90 | K27: 7.4 | L27: 6.2 | M27: 7.3 | N27: Tabla 3, la 1ra desde la izquierda | T27: 63 | U27: 2 ½ | V27: 1.3 | W27: 1.7 | X27: 2.0 | Y27: 0.9 | Z27: 0.8 | AA27: 1.0 | AB27: 0.5 | AC27: 0.9 | AD27: 1.9 | AE27: 0.4 | AF27: 21.0 | AG27: 10.0 | AH27: 1.3 | AI27: 4.3 | AJ27: 4.3 | AK27: 17.0 | AL27: 1.9 | AM27: 5.2 | AN27: 8.1
A28: Succión | B28: =+B32+2 -> 7.1 | C28: =+B28 -> 7.1 | D28: =+C28 -> 7.1 | E28: m | J28: Tee 2salida | K28: 22 | L28: 19 | M28: 22 | N28: Tabla 3, 5ta a la derecha | T28: 75 | U28: 3 | V28: 1.6 | W28: 2.1 | X28: 2.5 | Y28: 1.2 | Z28: 1.0 | AA28: 1.3 | AB28: 0.6 | AC28: 1.1 | AD28: 2.2 | AE28: 0.5 | AF28: 26.0 | AG28: 13.0 | AH28: 1.6 | AI28: 5.2 | AJ28: 5.2 | AK28: 20.0 | AL28: 2.2 | AM28: 6.3 | AN28: 9.7
A29: Impulsión | B29: =2035.06+0.3+10.5 -> 2045.86 | C29: =+B29 -> 2045.86 | D29: =+C29 -> 2045.86 | E29: m | J29: Curva 90 | K29: 7.4 | L29: 6.2 | M29: 7.3 | T29: 100 | U29: 4 | V29: 2.1 | W29: 2.8 | X29: 3.4 | Y29: 1.5 | Z29: 1.3 | AA29: 1.6 | AB29: 0.7 | AC29: 1.6 | AD29: 3.2 | AE29: 0.7 | AF29: 34.0 | AG29: 17.0 | AH29: 2.1 | AI29: 6.7 | AJ29: 6.7 | AK29: 23.0 | AL29: 3.2 | AM29: 6.4 | AN29: 12.9
J30: Valv. De Cierre | K30: 2.8 | L30: 2.6 | M30: 2.4 | N30: El dibujo mas grande, globo | T30: 125 | U30: 5 | V30: 2.7 | W30: 3.7 | X30: 4.2 | Y30: 1.9 | Z30: 1.6 | AA30: 2.1 | AB30: 0.9 | AC30: 2.0 | AD30: 4.0 | AE30: 0.9 | AF30: 43.0 | AG30: 21.0 | AH30: 2.7 | AI30: 8.4 | AJ30: 8.4 | AK30: 30.0 | AL30: 4.0 | AM30: 10.4 | AN30: 16.1
A31: Altura topográfica | J31: Total: | K31: =SUM(K26:K30) -> 129.7 | L31: =SUM(L26:L30) -> 112.1 | M31: =SUM(M26:M30) -> 129 | T31: 150 | U31: 6 | V31: 3.4 | W31: 4.3 | X31: 4.9 | Y31: 2.3 | Z31: 1.9 | AA31: 2.5 | AB31: 1.1 | AC31: 2.5 | AD31: 5.0 | AE31: 1.1 | AF31: 51.0 | AG31: 26.0 | AH31: 3.4 | AI31: 10.0 | AJ31: 10.0 | AK31: 39.0 | AL31: 5.0 | AM31: 12.5 | AN31: 19.3
A32: Succión | B32: =1+0.5+POTABILIZADORA!$B$270 -> 5.1 | C32: =+B32 -> 5.1 | D32: =+C32 -> 5.1 | E32: m | J32: Impulsión | K32: =+B13 -> 500 | L32: =+C13 -> 450 | M32: =+D13 -> 300 | T32: 200 | U32: 8 | V32: 4.3 | W32: 5.5 | X32: 6.4 | Y32: 3.0 | Z32: 2.4 | AA32: 3.3 | AB32: 1.5 | AC32: 3.5 | AD32: 6.0 | AE32: 1.4 | AF32: 67.0 | AG32: 34.0 | AH32: 4.3 | AI32: 13.0 | AJ32: 13.0 | AK32: 52.0 | AL32: 6.0 | AM32: 16.0 | AN32: 25.0
A33: Impulsión | B33: 18 | C33: =+B33 -> 18 | D33: =+C33 -> 18 | E33: m | J33: Curva 90 | K33: 6.2 | L33: 5.6 | M33: 6.1 | T33: 250 | U33: 10 | V33: 5.5 | W33: 6.7 | X33: 7.9 | Y33: 3.8 | Z33: 3.0 | AA33: 4.1 | AB33: 1.8 | AC33: 4.5 | AD33: 7.5 | AE33: 1.7 | AF33: 85.0 | AG33: 43.0 | AH33: 5.5 | AI33: 16.0 | AJ33: 16.0 | AK33: 65.0 | AL33: 7.5 | AM33: 20.0 | AN33: 32.0
J34: Valv. De Retenc | K34: 24.1 | L34: 20.1 | M34: 24 | N34: 2do de la derecha | T34: 300 | U34: 11 | V34: 6.1 | W34: 7.9 | X34: 9.5 | Y34: 4.6 | Z34: 3.6 | AA34: 4.8 | AB34: 2.2 | AC34: 5.5 | AD34: 9.0 | AE34: 2.2 | AF34: 102.0 | AG34: 51.0 | AH34: 6.1 | AI34: 19.0 | AJ34: 19.0 | AK34: 78.0 | AL34: 9.0 | AM34: 24.0 | AN34: 38.0
A35: Velocidad en la tubería | J35: Valv. De Cierre | K35: 2.6 | L35: 1.3 | M35: 2.2 | T35: 350 | U35: 12 | V35: 7.3 | W35: 9.5 | X35: 10.5 | Y35: 5.3 | Z35: 4.4 | AA35: 5.4 | AB35: 2.5 | AC35: 6.2 | AD35: 11.0 | AE35: 2.4 | AF35: 120.0 | AG35: 60.0 | AH35: 7.3 | AI35: 22.0 | AJ35: 22.0 | AK35: 90.0 | AL35: 11.0 | AM35: 28.0 | AN35: 45.0
A36: Succión | B36: =+$B$7/(PI()*((B12/1000)^2)/4) -> 0.78061159 | C36: =+$B$7/(PI()*((C12/1000)^2)/4) -> 0.94454002 | D36: =+B7/(PI()*((D12/1000)^2)/4) -> 1.9276327 | E36: m/s | J36: Tee lateral | K36: 19 | L36: 16 | M36: 19 | N36: 6to de la derecha | T36: 400 | U36: 13.5 | V36: 4.4 | W36: 5.6 | X36: 6.5 | Y36: 3.16 | Z36: 2.5 | AA36: 3.4 | AB36: 1.11 | AC36: 3.6 | AD36: 6.1 | AE36: 1.10 | AF36: 67.1 | AG36: 34.1 | AH36: 4.4 | AI36: 13.0 | AJ36: 13.0 | AK36: 52.1 | AL36: 6.1 | AM36: 16.1 | AN36: 25.1
A37: Impulsión | B37: =+$B$7/(PI()*((B13/1000)^2)/4) -> 0.94454002 | C37: =+$B$7/(PI()*((C13/1000)^2)/4) -> 1.1660988 | D37: =+B7/(PI()*((D13/1000)^2)/4) -> 2.6237223 | E37: m/s | J37: Total: | K37: =SUM(K33:K36) -> 51.9 | L37: =SUM(L33:L36) -> 43 | M37: =SUM(M33:M36) -> 51.3 | T37: 450 | U37: 14.8 | V37: 5.6 | W37: 6.8 | X37: 7.10 | Y37: 3.24 | Z37: 3.12 | AA37: 4.15 | AB37: 1.14 | AC37: 4.6 | AD37: 7.6 | AE37: 1.13 | AF37: 85.1 | AG37: 43.1 | AH37: 5.6 | AI37: 16.0 | AJ37: 16.0 | AK37: 65.1 | AL37: 7.6 | AM37: 20.1 | AN37: 32.1
T38: 500 | U38: 16.1 | V38: 6.2 | W38: 7.10 | X38: 9.6 | Y38: 4.7 | Z38: 3.18 | AA38: 4.22 | AB38: 2.8 | AC38: 5.6 | AD38: 9.1 | AE38: 2.6 | AF38: 102.1 | AG38: 51.1 | AH38: 6.2 | AI38: 19.0 | AJ38: 19.0 | AK38: 78.1 | AL38: 9.1 | AM38: 24.1 | AN38: 38.1
A39: Presión de llegada al reservorio | B39: 1 | C39: =+B39 -> 1 | D39: =+C39 -> 1 | E39: m | T39: 550 | U39: 17.4 | V39: 7.4 | W39: 9.6 | X39: 10.6 | Y39: 5.4 | Z39: 4.5 | AA39: 5.5 | AB39: 2.11 | AC39: 6.3 | AD39: 11.1 | AE39: 2.8 | AF39: 120.1 | AG39: 60.1 | AH39: 7.4 | AI39: 22.0 | AJ39: 22.0 | AK39: 90.1 | AL39: 11.1 | AM39: 28.1 | AN39: 45.1
A41: Altura Manométrica o Gradiente Hidraúlico
A42: Succión | B42: =+B32+(B28+B24)*B20+((B36^2)/(2*9.8)) -> 5.3466781 | C42: =+C32+(C28+C24)*C20+((C36^2)/(2*9.8)) -> 5.4446067 | D42: =+D32+(D28+D24)*D20+((D36^2)/(2*9.8)) -> 7.2360902 | E42: m.c.a.
A43: Impulsión | B43: =+B33+(B29+B25)*B21+((B37^2)/(2*9.8)) -> 23.309076 | C43: =+C33+(C29+C25)*C21+((C37^2)/(2*9.8)) -> 26.833646 | D43: =+D33+(D29+D25)*D21+((D37^2)/(2*9.8)) -> 81.988313 | E43: m.c.a.
A44: Total | B44: =+B43+B42+B39 -> 29.655754 | C44: =+C43+C42+C39 -> 33.278253 | D44: =+D43+D42+D39 -> 90.224404 | E44: m.c.a.
L45: TABLA 6: Rendimiento para bombas centrifugas
L46: Q (l/s) | M46: 2.5 | N46: 5 | O46: 7.5 | P46: 10 | Q46: 15 | R46: 20 | S46: 25 | T46: 30 | U46: 40 | V46: 50 | W46: 100 | X46: 200
A47: Potencia de la Bomba | L47: hb [%] | M47: 45 | N47: 52 | O47: 61 | P47: 66 | Q47: 68 | R47: 71 | S47: 75 | T47: 80 | U47: 84 | V47: 85 | W47: 87 | X47: 88
A48: Pb | B48: =1000*B44*$B$7/75/H49 -> 83.332669 | C48: =1000*C44*$B$7/75/I49 -> 93.511891 | D48: =1000*D44*$B$7/75/J49 -> 253.53057 | E48: cv
B49: =1.014*B48 -> 84.499326 | C49: =1.014*C48 -> 94.821057 | D49: =1.014*D48 -> 257.08 | E49: HP | F49: =+B2*1000/86400 -> 154.55 | G49: ∩bomba | H49: 0.88 | I49: =+H49 -> 0.88 | J49: =+I49 -> 0.88 | L49: TABLA 7:Rendimiento de motores eléctricos
A50: Pmb | B50: =+B49/H50 -> 93.88814 | C50: =+C49/I50 -> 105.35673 | D50: =+D49/I50 -> 285.64445 | E50: HP | G50: ∩motor | H50: 0.9 | I50: 0.9 | J50: 0.9 | L50: HP | M50: ¼ | O50: ½ | P50: ¾ | Q50: 1 | R50: 1½ | S50: 2 | T50: 3 | U50: 4 | V50: 5 | W50: 6 | X50: 7½ | Y50: 10 | Z50: 12 | AA50: 15 | AB50: 20 | AC50: 30 | AD50: 50 | AE50: 100
A51: Holgura | B51: 10 | C51: 11 | D51: 10 | E51: % | L51: hm [%] | M51: 61 | N51: 63 | O51: 64 | P51: 67 | Q51: 72 | R51: 73 | S51: 75 | T51: 77 | U51: 79 | V51: 81 | W51: 82 | X51: 82.4 | Y51: 83 | Z51: 84 | AA51: 85 | AB51: 86 | AC51: 87 | AD51: 88 | AE51: 90
A52: Phmb | B52: =(1+B51/100)*B50 -> 103.27695 | C52: =(1+C51/100)*C50 -> 116.94597 | D52: =(1+D51/100)*D50 -> 314.20889 | E52: HP
A53: Padop | C53: 120 | D53: HP | F53: VER TABLA 8 de la NORMA 68
F54: Holgura Tipo de bomba 50% Para bombas de hasta 2 HP 30% Para bombas de 2 a 5 HP 20% Para bombas de 5 a 10 HP 15% Para bombas de 10 a 20 HP 10% Para bombas de más de 20 HP
A55: Pozo de bombeo
A56: Altura mínima
A57: Por cavitación = | B57: =+((B36^2)/(2*9.8))+0.2 -> 0.23108951 | C57: =+((C36^2)/(2*9.8))+0.2 -> 0.24551816 | D57: =+((D36^2)/(2*9.8))+0.2 -> 0.38957999 | E57: m
A58: Por serguridad > | B58: 0.5 | E58: m
A59: Adopta el mayor | B59: 0.5 | E59: m
A61: Selección del diámetro del mínimo costo
A62: Se debe escogen tres (3) diámetros comerciales en torno al valor de Bresse, para poder seleccionar el diámetro más adecuado
A63: Se realiza un análisis de costos que involucra: | E63: Costo
A64: • costos de tuberías | D64: Inversión | E64: $tuberia | F64: y bomba
A65: • costos de los equipos de bombeo | D65: Operación | E65: $ potencia | F65: mantenimiento
A66: • costos de operación y mantenimiento | D66: Vida Útil | E66: Bomba 7 años | F66: Tuberia 50 años

Sheet Caudales
A2: 4- CAUDALES
A6: 1ra iteración
A7: CIRCUITO | C7: TRAMO | D7: DIAM.(m) | E7: LONG.(m) | F7: CAUDAL (m3/s) | G7: VELOC.(m/s) | H7: J (m/m) | I7: Hi(m) | J7: Hi/Qi | K7: CORRECCIÓN | M7: CAUDAL (m3/s)
A8: PROPIO | B8: COMUN | K8: PROPIA | L8: COMUN
A9: I | C9: ='Datos Inic'!B11 -> AB | D9: ='Datos Inic'!L11 -> 0.2 | E9: ='Datos Inic'!C11 -> 224 | F9: ='Datos Inic'!H11/1000 -> 0.02704625 | G9: =+F9*4/(3.1415*D9^2) -> 0.86093427 | H9: =10.643*140^(-1.85)*D9^(-4.87)*ABS(F9)^1.85*IF(F9<0,-1,1) -> 0.0036316934 | I9: =+H9*E9 -> 0.81349932 | J9: =+I9/F9 -> 30.078082 | K9: =-I13/(J13*1.851) -> -0.01071584 | M9: =+F9+K9+L9 -> 0.01633041
C10: ='Datos Inic'!B12 -> RB | D10: ='Datos Inic'!L12 -> 0.3 | E10: ='Datos Inic'!C12 -> 336 | F10: =-'Datos Inic'!H12/1000 -> -0.077275 | G10: =+F10*4/(3.1415*D10^2) -> -1.0932499 | H10: =10.643*140^(-1.85)*D10^(-4.87)*ABS(F10)^1.85*IF(F10<0,-1,1) -> -0.0035157571 | I10: =+H10*E10 -> -1.1812944 | J10: =+I10/F10 -> 15.286889 | K10: =-I13/(J13*1.851) -> -0.01071584 | M10: =+F10+K10+L10 -> -0.08799084
B11: II | C11: ='Datos Inic'!B13 -> RQ | D11: ='Datos Inic'!L13 -> 0.35 | E11: ='Datos Inic'!C13 -> 224 | F11: ='Datos Inic'!H13/1000 -> 0.1004575 | G11: =+F11*4/(3.1415*D11^2) -> 1.0441652 | H11: =10.643*140^(-1.85)*D11^(-4.87)*ABS(F11)^1.85*IF(F11<0,-1,1) -> 0.002696393 | I11: =+H11*E11 -> 0.60399204 | J11: =+I11/F11 -> 6.0124136 | K11: =-I13/(J13*1.851) -> -0.01071584 | L11: =-K20 -> -0.044018 | M11: =+F11+K11+L11 -> 0.04572366
C12: ='Datos Inic'!B14 -> QA | D12: ='Datos Inic'!L14 -> 0.25 | E12: ='Datos Inic'!C14 -> 336 | F12: ='Datos Inic'!H14/1000 -> 0.05022875 | G12: =+F12*4/(3.1415*D12^2) -> 1.0232819 | H12: =10.643*140^(-1.85)*D12^(-4.87)*ABS(F12)^1.85*IF(F12<0,-1,1) -> 0.0038505365 | I12: =+H12*E12 -> 1.2937802 | J12: =+I12/F12 -> 25.757763 | K12: =-I13/(J13*1.851) -> -0.01071584 | M12: =+F12+K12+L12 -> 0.03951291
H13: SUMA | I13: =+SUM(I9:I12) -> 1.5299772 | J13: =+SUM(J9:J12) -> 77.135148
A15: CIRCUITO | C15: TRAMO | D15: DIAM.(m) | E15: LONG.(m) | F15: CAUDAL (m3/s) | G15: VELOC.(m/s) | H15: J (m/m) | I15: Hi(m) | J15: Hi/Qi | K15: CORRECCIÓN | M15: CAUDAL (m3/s)
A16: PROPIO | B16: COMUN | K16: PROPIA | L16: COMUN
A17: II | C17: ='Datos Inic'!B15 -> HR | D17: ='Datos Inic'!L15 -> 0.25 | E17: ='Datos Inic'!C15 -> 336 | F17: =-'Datos Inic'!H15/1000 -> -0.05022875 | G17: =+F17*4/(3.1415*D17^2) -> -1.0232819 | H17: =10.643*140^(-1.85)*D17^(-4.87)*ABS(F17)^1.85*IF(F17<0,-1,1) -> -0.0038505365 | I17: =+H17*E17 -> -1.2937802 | J17: =+I17/F17 -> 25.757763 | K17: =-I21/(J21*1.851) -> 0.044018 | M17: =+F17+K17+L17 -> -0.0062107499
C18: ='Datos Inic'!B16 -> GH | D18: ='Datos Inic'!L16 -> 0.3 | E18: ='Datos Inic'!C16 -> 224 | F18: =-'Datos Inic'!H16/1000 -> -0.077275 | G18: =+F18*4/(3.1415*D18^2) -> -1.0932499 | H18: =10.643*140^(-1.85)*D18^(-4.87)*ABS(F18)^1.85*IF(F18<0,-1,1) -> -0.0035157571 | I18: =+H18*E18 -> -0.78752959 | J18: =+I18/F18 -> 10.19126 | K18: =-I21/(J21*1.851) -> 0.044018 | M18: =+F18+K18+L18 -> -0.033257
C19: ='Datos Inic'!B17 -> RQ | D19: ='Datos Inic'!L17 -> 0.35 | E19: ='Datos Inic'!C17 -> 224 | F19: ='Datos Inic'!H17/1000 -> 0.1004575 | G19: =+F19*4/(3.1415*D19^2) -> 1.0441652 | H19: =10.643*140^(-1.85)*D19^(-4.87)*ABS(F19)^1.85*IF(F19<0,-1,1) -> 0.002696393 | I19: =+H19*E19 -> 0.60399204 | J19: =+I19/F19 -> 6.0124136 | K19: =-I21/(J21*1.851) -> 0.044018 | M19: =+F19+K19+L19 -> 0.1444755
B20: I | C20: ='Datos Inic'!B18 -> GQ | D20: ='Datos Inic'!L18 -> 0.35 | E20: ='Datos Inic'!C18 -> 336 | F20: =-'Datos Inic'!H18/1000 -> -0.200915 | G20: =+F20*4/(3.1415*D20^2) -> -2.0883304 | H20: =10.643*140^(-1.85)*D20^(-4.87)*ABS(F20)^1.85*IF(F20<0,-1,1) -> -0.0097205019 | I20: =+H20*E20 -> -3.2660886 | J20: =+I20/F20 -> 16.256072 | K20: =-I21/(J21*1.851) -> 0.044018 | L20: =-K11 -> 0.01071584 | M20: =+F20+K20+L20 -> -0.14618116
H21: SUMA | I21: =+SUM(I17:I20) -> -4.7434064 | J21: =+SUM(J17:J20) -> 58.217508
A23: 2da iteración
A24: =A7 -> CIRCUITO | C24: =C7 -> TRAMO | D24: =D7 -> DIAM.(m) | E24: =E7 -> LONG.(m) | F24: CAUDAL (m3/s) | G24: VELOC.(m/s) | H24: J (m/m) | I24: Hi(m) | J24: Hi/Qi | K24: CORRECCIÓN | M24: CAUDAL (m3/s)
A25: =A8 -> PROPIO | B25: =B8 -> COMUN | K25: PROPIA | L25: COMUN
A26: =A9 -> I | C26: =C9 -> AB | D26: =D9 -> 0.2 | E26: =E9 -> 224 | F26: =M9 -> 0.01633041 | G26: =+F26*4/(3.1415*D26^2) -> 0.51982842 | H26: =10.643*140^(-1.85)*D26^(-4.87)*ABS(F26)^1.85*IF(F26<0,-1,1) -> 0.0014280905 | I26: =+H26*E26 -> 0.31989226 | J26: =+I26/F26 -> 19.588747 | K26: =-I30/(J30*1.851) -> 0.0018802528 | M26: =+F26+K26+L26 -> 0.018210663
C27: =C10 -> RB | D27: =D10 -> 0.3 | E27: =E10 -> 336 | F27: =M10 -> -0.08799084 | G27: =+F27*4/(3.1415*D27^2) -> -1.2448525 | H27: =10.643*140^(-1.85)*D27^(-4.87)*ABS(F27)^1.85*IF(F27<0,-1,1) -> -0.0044704989 | I27: =+H27*E27 -> -1.5020876 | J27: =+I27/F27 -> 17.070955 | K27: =-I30/(J30*1.851) -> 0.0018802528 | M27: =+F27+K27+L27 -> -0.086110587
B28: =B11 -> II | C28: =C11 -> RQ | D28: =D11 -> 0.35 | E28: =E11 -> 224 | F28: =M11 -> 0.04572366 | G28: =+F28*4/(3.1415*D28^2) -> 0.47525623 | H28: =10.643*140^(-1.85)*D28^(-4.87)*ABS(F28)^1.85*IF(F28<0,-1,1) -> 0.00062860328 | I28: =+H28*E28 -> 0.14080713 | J28: =+I28/F28 -> 3.0795246 | K28: =-I30/(J30*1.851) -> 0.0018802528 | L28: =-K37 -> -0.014856872 | M28: =+F28+K28+L28 -> 0.03274704
C29: =C12 -> QA | D29: =D12 -> 0.25 | E29: =E12 -> 336 | F29: =M12 -> 0.03951291 | G29: =+F29*4/(3.1415*D29^2) -> 0.80497413 | H29: =10.643*140^(-1.85)*D29^(-4.87)*ABS(F29)^1.85*IF(F29<0,-1,1) -> 0.0024701682 | I29: =+H29*E29 -> 0.82997652 | J29: =+I29/F29 -> 21.005199 | K29: =-I30/(J30*1.851) -> 0.0018802528 | M29: =+F29+K29+L29 -> 0.041393163
H30: SUMA | I30: =+SUM(I26:I29) -> -0.21141173 | J30: =+SUM(J26:J29) -> 60.744425
A32: =A15 -> CIRCUITO | C32: =C15 -> TRAMO | D32: =D15 -> DIAM.(m) | E32: =E15 -> LONG.(m) | F32: CAUDAL (m3/s) | G32: VELOC.(m/s) | H32: J (m/m) | I32: Hi(m) | J32: Hi/Qi | K32: CORRECCIÓN | M32: CAUDAL (m3/s)
A33: =A16 -> PROPIO | B33: =B16 -> COMUN | K33: PROPIA | L33: COMUN
A34: =A17 -> II | C34: =C17 -> HR | D34: =D17 -> 0.25 | E34: =E17 -> 336 | F34: =M17 -> -0.0062107499 | G34: =+F34*4/(3.1415*D34^2) -> -0.12652809 | H34: =10.643*140^(-1.85)*D34^(-4.87)*ABS(F34)^1.85*IF(F34<0,-1,1) -> -8.0551907e-05 | I34: =+H34*E34 -> -0.027065441 | J34: =+I34/F34 -> 4.3578378 | K34: =-I38/(J38*1.851) -> 0.014856872 | M34: =+F34+K34+L34 -> 0.008646122
C35: =C18 -> GH | D35: =D18 -> 0.3 | E35: =E18 -> 224 | F35: =M18 -> -0.033257 | G35: =+F35*4/(3.1415*D35^2) -> -0.47050418 | H35: =10.643*140^(-1.85)*D35^(-4.87)*ABS(F35)^1.85*IF(F35<0,-1,1) -> -0.00073897605 | I35: =+H35*E35 -> -0.16553064 | J35: =+I35/F35 -> 4.9773171 | K35: =-I38/(J38*1.851) -> 0.014856872 | M35: =+F35+K35+L35 -> -0.018400128
C36: =C19 -> RQ | D36: =D19 -> 0.35 | E36: =E19 -> 224 | F36: =M19 -> 0.1444755 | G36: =+F36*4/(3.1415*D36^2) -> 1.5016926 | H36: =10.643*140^(-1.85)*D36^(-4.87)*ABS(F36)^1.85*IF(F36<0,-1,1) -> 0.0052812302 | I36: =+H36*E36 -> 1.1829956 | J36: =+I36/F36 -> 8.1882089 | K36: =-I38/(J38*1.851) -> 0.014856872 | M36: =+F36+K36+L36 -> 0.15933237
B37: =B20 -> I | C37: =C20 -> GQ | D37: =D20 -> 0.35 | E37: =E20 -> 336 | F37: =M20 -> -0.14618116 | G37: =+F37*4/(3.1415*D37^2) -> -1.5194214 | H37: =10.643*140^(-1.85)*D37^(-4.87)*ABS(F37)^1.85*IF(F37<0,-1,1) -> -0.0053971553 | I37: =+H37*E37 -> -1.8134442 | J37: =+I37/F37 -> 12.405458 | K37: =-I38/(J38*1.851) -> 0.014856872 | L37: =-K28 -> -0.0018802528 | M37: =+F37+K37+L37 -> -0.13320454
H38: SUMA | I38: =+SUM(I34:I37) -> -0.82304468 | J38: =+SUM(J34:J37) -> 29.928822
A40: 3ra iteración
A41: =A7 -> CIRCUITO | C41: =C7 -> TRAMO | D41: =D7 -> DIAM.(m) | E41: =E7 -> LONG.(m) | F41: CAUDAL (m3/s) | G41: VELOC.(m/s) | H41: J (m/m) | I41: Hi(m) | J41: Hi/Qi | K41: CORRECCIÓN | M41: CAUDAL (m3/s)
A42: =A8 -> PROPIO | B42: =B8 -> COMUN | K42: PROPIA | L42: COMUN
A43: =A9 -> I | C43: =C9 -> AB | D43: =D9 -> 0.2 | E43: =E9 -> 224 | F43: =M26 -> 0.018210663 | G43: =+F43*4/(3.1415*D43^2) -> 0.57968049 | H43: =10.643*140^(-1.85)*D43^(-4.87)*ABS(F43)^1.85*IF(F43<0,-1,1) -> 0.0017470838 | I43: =+H43*E43 -> 0.39134678 | J43: =+I43/F43 -> 21.48998 | K43: =-I47/(J47*1.851) -> 0.0006183943 | M43: =+F43+K43+L43 -> 0.018829057
C44: =C10 -> RB | D44: =D10 -> 0.3 | E44: =E10 -> 336 | F44: =M27 -> -0.086110587 | G44: =+F44*4/(3.1415*D44^2) -> -1.2182515 | H44: =10.643*140^(-1.85)*D44^(-4.87)*ABS(F44)^1.85*IF(F44<0,-1,1) -> -0.0042953772 | I44: =+H44*E44 -> -1.4432467 | J44: =+I44/F44 -> 16.760387 | K44: =-I47/(J47*1.851) -> 0.0006183943 | M44: =+F44+K44+L44 -> -0.085492193
B45: =B11 -> II | C45: =C11 -> RQ | D45: =D11 -> 0.35 | E45: =E11 -> 224 | F45: =M28 -> 0.03274704 | G45: =+F45*4/(3.1415*D45^2) -> 0.34037597 | H45: =10.643*140^(-1.85)*D45^(-4.87)*ABS(F45)^1.85*IF(F45<0,-1,1) -> 0.00033898784 | I45: =+H45*E45 -> 0.075933277 | J45: =+I45/F45 -> 2.3187829 | K45: =-I47/(J47*1.851) -> 0.0006183943 | L45: =-K54 -> -0.0021232732 | M45: =+F45+K45+L45 -> 0.031242162
C46: =C12 -> QA | D46: =D12 -> 0.25 | E46: =E12 -> 336 | F46: =M29 -> 0.041393163 | G46: =+F46*4/(3.1415*D46^2) -> 0.84327945 | H46: =10.643*140^(-1.85)*D46^(-4.87)*ABS(F46)^1.85*IF(F46<0,-1,1) -> 0.0026920138 | I46: =+H46*E46 -> 0.90451663 | J46: =+I46/F46 -> 21.851837 | K46: =-I47/(J47*1.851) -> 0.0006183943 | M46: =+F46+K46+L46 -> 0.042011557
H47: SUMA | I47: =+SUM(I43:I46) -> -0.071450048 | J47: =+SUM(J43:J46) -> 62.420987
A49: =A15 -> CIRCUITO | C49: =C15 -> TRAMO | D49: =D15 -> DIAM.(m) | E49: =E15 -> LONG.(m) | F49: CAUDAL (m3/s) | G49: VELOC.(m/s) | H49: J (m/m) | I49: Hi(m) | J49: Hi/Qi | K49: CORRECCIÓN | M49: CAUDAL (m3/s)
A50: =A16 -> PROPIO | B50: =B16 -> COMUN | K50: PROPIA | L50: COMUN
A51: =A17 -> II | C51: =C17 -> HR | D51: =D17 -> 0.25 | E51: =E17 -> 336 | F51: =M34 -> 0.008646122 | G51: =+F51*4/(3.1415*D51^2) -> 0.17614255 | H51: =10.643*140^(-1.85)*D51^(-4.87)*ABS(F51)^1.85*IF(F51<0,-1,1) -> 0.00014855213 | I51: =+H51*E51 -> 0.049913514 | J51: =+I51/F51 -> 5.7729366 | K51: =-I55/(J55*1.851) -> 0.0021232732 | M51: =+F51+K51+L51 -> 0.010769395
C52: =C18 -> GH | D52: =D18 -> 0.3 | E52: =E18 -> 224 | F52: =M35 -> -0.018400128 | G52: =+F52*4/(3.1415*D52^2) -> -0.26031624 | H52: =10.643*140^(-1.85)*D52^(-4.87)*ABS(F52)^1.85*IF(F52<0,-1,1) -> -0.00024720955 | I52: =+H52*E52 -> -0.05537494 | J52: =+I52/F52 -> 3.0094867 | K52: =-I55/(J55*1.851) -> 0.0021232732 | M52: =+F52+K52+L52 -> -0.016276855
C53: =C19 -> RQ | D53: =D19 -> 0.35 | E53: =E19 -> 224 | F53: =M36 -> 0.15933237 | G53: =+F53*4/(3.1415*D53^2) -> 1.6561164 | H53: =10.643*140^(-1.85)*D53^(-4.87)*ABS(F53)^1.85*IF(F53<0,-1,1) -> 0.0063296291 | I53: =+H53*E53 -> 1.4178369 | J53: =+I53/F53 -> 8.8986117 | K53: =-I55/(J55*1.851) -> 0.0021232732 | M53: =+F53+K53+L53 -> 0.16145565
B54: =B20 -> I | C54: =C20 -> GQ | D54: =D20 -> 0.35 | E54: =E20 -> 336 | F54: =M37 -> -0.13320454 | G54: =+F54*4/(3.1415*D54^2) -> -1.3845411 | H54: =10.643*140^(-1.85)*D54^(-4.87)*ABS(F54)^1.85*IF(F54<0,-1,1) -> -0.0045443945 | I54: =+H54*E54 -> -1.5269165 | J54: =+I54/F54 -> 11.462947 | K54: =-I55/(J55*1.851) -> 0.0021232732 | L54: =-K45 -> -0.0006183943 | M54: =+F54+K54+L54 -> -0.13169966
H55: SUMA | I55: =+SUM(I51:I54) -> -0.11454106 | J55: =+SUM(J51:J54) -> 29.143982
A57: 4ta iteración
A58: =A7 -> CIRCUITO | C58: =C7 -> TRAMO | D58: =D7 -> DIAM.(m) | E58: =E7 -> LONG.(m) | F58: CAUDAL (m3/s) | G58: VELOC.(m/s) | H58: J (m/m) | I58: Hi(m) | J58: Hi/Qi | K58: CORRECCIÓN | M58: CAUDAL (m3/s) | O58: DIAM.(m)
A59: =A8 -> PROPIO | B59: =B8 -> COMUN | K59: PROPIA | L59: COMUN
A60: =A9 -> I | C60: =C9 -> AB | D60: =D9 -> 0.2 | E60: =E9 -> 224 | F60: =M43 -> 0.018829057 | G60: =+F60*4/(3.1415*D60^2) -> 0.59936517 | H60: =10.643*140^(-1.85)*D60^(-4.87)*ABS(F60)^1.85*IF(F60<0,-1,1) -> 0.0018584204 | I60: =+H60*E60 -> 0.41628617 | J60: =+I60/F60 -> 22.108711 | K60: =-I64/(J64*1.851) -> 7.3314902e-05 | M60: =+F60+K60+L60 -> 0.018902372 | O60: =+D60 -> 0.2
C61: =C10 -> RB | D61: =D10 -> 0.3 | E61: =E10 -> 336 | F61: =M44 -> -0.085492193 | G61: =+F61*4/(3.1415*D61^2) -> -1.2095028 | H61: =10.643*140^(-1.85)*D61^(-4.87)*ABS(F61)^1.85*IF(F61<0,-1,1) -> -0.0042384848 | I61: =+H61*E61 -> -1.4241309 | J61: =+I61/F61 -> 16.658023 | K61: =-I64/(J64*1.851) -> 7.3314902e-05 | M61: =+F61+K61+L61 -> -0.085418878 | O61: =+D61 -> 0.3
B62: =B11 -> II | C62: =C11 -> RQ | D62: =D11 -> 0.35 | E62: =E11 -> 224 | F62: =M45 -> 0.031242162 | G62: =+F62*4/(3.1415*D62^2) -> 0.32473411 | H62: =10.643*140^(-1.85)*D62^(-4.87)*ABS(F62)^1.85*IF(F62<0,-1,1) -> 0.00031073259 | I62: =+H62*E62 -> 0.0696041 | J62: =+I62/F62 -> 2.22789 | K62: =-I64/(J64*1.851) -> 7.3314902e-05 | L62: =-K71 -> -0.00020469868 | M62: =+F62+K62+L62 -> 0.031110778 | O62: =+D62 -> 0.35
C63: =C12 -> QA | D63: =D12 -> 0.25 | E63: =E12 -> 336 | F63: =M46 -> 0.042011557 | G63: =+F63*4/(3.1415*D63^2) -> 0.85587765 | H63: =10.643*140^(-1.85)*D63^(-4.87)*ABS(F63)^1.85*IF(F63<0,-1,1) -> 0.0027668881 | I63: =+H63*E63 -> 0.92967439 | J63: =+I63/F63 -> 22.129015 | K63: =-I64/(J64*1.851) -> 7.3314902e-05 | M63: =+F63+K63+L63 -> 0.042084872 | O63: =+D63 -> 0.25
H64: SUMA | I64: =+SUM(I60:I63) -> -0.0085662492 | J64: =+SUM(J60:J63) -> 63.123639
A66: =A15 -> CIRCUITO | C66: =C15 -> TRAMO | D66: =D15 -> DIAM.(m) | E66: =E15 -> LONG.(m) | F66: CAUDAL (m3/s) | G66: VELOC.(m/s) | H66: J (m/m) | I66: Hi(m) | J66: Hi/Qi | K66: CORRECCIÓN | M66: CAUDAL (m3/s) | O66: DIAM.(m)
A67: =A16 -> PROPIO | B67: =B16 -> COMUN | K67: PROPIA | L67: COMUN
A68: =A17 -> II | C68: =C17 -> HR | D68: =D17 -> 0.25 | E68: =E17 -> 336 | F68: =M51 -> 0.010769395 | G68: =+F68*4/(3.1415*D68^2) -> 0.21939879 | H68: =10.643*140^(-1.85)*D68^(-4.87)*ABS(F68)^1.85*IF(F68<0,-1,1) -> 0.00022300433 | I68: =+H68*E68 -> 0.074929454 | J68: =+I68/F68 -> 6.9576287 | K68: =-I72/(J72*1.851) -> 0.00020469868 | M68: =+F68+K68+L68 -> 0.010974094 | O68: =+D68 -> 0.25
C69: =C18 -> GH | D69: =D18 -> 0.3 | E69: =E18 -> 224 | F69: =M52 -> -0.016276855 | G69: =+F69*4/(3.1415*D69^2) -> -0.23027718 | H69: =10.643*140^(-1.85)*D69^(-4.87)*ABS(F69)^1.85*IF(F69<0,-1,1) -> -0.00019703895 | I69: =+H69*E69 -> -0.044136725 | J69: =+I69/F69 -> 2.7116249 | K69: =-I72/(J72*1.851) -> 0.00020469868 | M69: =+F69+K69+L69 -> -0.016072156 | O69: =+D69 -> 0.3
C70: =C19 -> RQ | D70: =D19 -> 0.35 | E70: =E19 -> 224 | F70: =M53 -> 0.16145565 | G70: =+F70*4/(3.1415*D70^2) -> 1.6781859 | H70: =10.643*140^(-1.85)*D70^(-4.87)*ABS(F70)^1.85*IF(F70<0,-1,1) -> 0.006486558 | I70: =+H70*E70 -> 1.452989 | J70: =+I70/F70 -> 8.9993074 | K70: =-I72/(J72*1.851) -> 0.00020469868 | M70: =+F70+K70+L70 -> 0.16166034 | O70: =+D70 -> 0.35
B71: =B20 -> I | C71: =C20 -> GQ | D71: =D20 -> 0.35 | E71: =E20 -> 336 | F71: =M54 -> -0.13169966 | G71: =+F71*4/(3.1415*D71^2) -> -1.3688993 | H71: =10.643*140^(-1.85)*D71^(-4.87)*ABS(F71)^1.85*IF(F71<0,-1,1) -> -0.0044498712 | I71: =+H71*E71 -> -1.4951567 | J71: =+I71/F71 -> 11.352776 | K71: =-I72/(J72*1.851) -> 0.00020469868 | L71: =-K62 -> -7.3314902e-05 | M71: =+F71+K71+L71 -> -0.13156828 | O71: =+D71 -> 0.35
H72: SUMA | I72: =+SUM(I68:I71) -> -0.011375002 | J72: =+SUM(J68:J71) -> 30.021337
A74: 5ta iteración
A75: =A7 -> CIRCUITO | C75: =C7 -> TRAMO | D75: =D7 -> DIAM.(m) | E75: =E7 -> LONG.(m) | F75: CAUDAL (m3/s) | G75: VELOC.(m/s) | H75: J (m/m) | I75: Hi(m) | J75: Hi/Qi | K75: CORRECCIÓN | M75: CAUDAL (m3/s) | O75: DIAM.(m)
A76: =A8 -> PROPIO | B76: =B8 -> COMUN | K76: PROPIA | L76: COMUN
A77: =A9 -> I | C77: =C9 -> AB | D77: =D9 -> 0.2 | E77: =E9 -> 224 | F77: =M60 -> 0.018902372 | G77: =+F77*4/(3.1415*D77^2) -> 0.60169892 | H77: =10.643*140^(-1.85)*D77^(-4.87)*ABS(F77)^1.85*IF(F77<0,-1,1) -> 0.0018718294 | I77: =+H77*E77 -> 0.41928979 | J77: =+I77/F77 -> 22.181862 | K77: =-I81/(J81*1.851) -> 7.1878285e-06 | M77: =+F77+K77+L77 -> 0.01890956 | O77: =+D77 -> 0.2
C78: =C10 -> RB | D78: =D10 -> 0.3 | E78: =E10 -> 336 | F78: =M61 -> -0.085418878 | G78: =+F78*4/(3.1415*D78^2) -> -1.2084656 | H78: =10.643*140^(-1.85)*D78^(-4.87)*ABS(F78)^1.85*IF(F78<0,-1,1) -> -0.004231763 | I78: =+H78*E78 -> -1.4218724 | J78: =+I78/F78 -> 16.64588 | K78: =-I81/(J81*1.851) -> 7.1878285e-06 | M78: =+F78+K78+L78 -> -0.08541169 | O78: =+D78 -> 0.3
B79: =B11 -> II | C79: =C11 -> RQ | D79: =D11 -> 0.35 | E79: =E11 -> 224 | F79: =M62 -> 0.031110778 | G79: =+F79*4/(3.1415*D79^2) -> 0.3233685 | H79: =10.643*140^(-1.85)*D79^(-4.87)*ABS(F79)^1.85*IF(F79<0,-1,1) -> 0.00030831945 | I79: =+H79*E79 -> 0.069063558 | J79: =+I79/F79 -> 2.2199238 | K79: =-I81/(J81*1.851) -> 7.1878285e-06 | L79: =-K88 -> -2.744816e-05 | M79: =+F79+K79+L79 -> 0.031090517 | O79: =+D79 -> 0.35
C80: =C12 -> QA | D80: =D12 -> 0.25 | E80: =E12 -> 336 | F80: =M63 -> 0.042084872 | G80: =+F80*4/(3.1415*D80^2) -> 0.85737125 | H80: =10.643*140^(-1.85)*D80^(-4.87)*ABS(F80)^1.85*IF(F80<0,-1,1) -> 0.0027758275 | I80: =+H80*E80 -> 0.93267803 | J80: =+I80/F80 -> 22.161836 | K80: =-I81/(J81*1.851) -> 7.1878285e-06 | M80: =+F80+K80+L80 -> 0.04209206 | O80: =+D80 -> 0.25
H81: SUMA | I81: =+SUM(I77:I80) -> -0.00084098158 | J81: =+SUM(J77:J80) -> 63.209501
A83: =A15 -> CIRCUITO | C83: =C15 -> TRAMO | D83: =D15 -> DIAM.(m) | E83: =E15 -> LONG.(m) | F83: CAUDAL (m3/s) | G83: VELOC.(m/s) | H83: J (m/m) | I83: Hi(m) | J83: Hi/Qi | K83: CORRECCIÓN | M83: CAUDAL (m3/s) | O83: DIAM.(m)
A84: =A16 -> PROPIO | B84: =B16 -> COMUN | K84: PROPIA | L84: COMUN
A85: =A17 -> II | C85: =C17 -> HR | D85: =D17 -> 0.25 | E85: =E17 -> 336 | F85: =M68 -> 0.010974094 | G85: =+F85*4/(3.1415*D85^2) -> 0.223569 | H85: =10.643*140^(-1.85)*D85^(-4.87)*ABS(F85)^1.85*IF(F85<0,-1,1) -> 0.00023090929 | I85: =+H85*E85 -> 0.07758552 | J85: =+I85/F85 -> 7.0698794 | K85: =-I89/(J89*1.851) -> 2.744816e-05 | M85: =+F85+K85+L85 -> 0.011001542 | O85: =+D85 -> 0.25
C86: =C18 -> GH | D86: =D18 -> 0.3 | E86: =E18 -> 224 | F86: =M69 -> -0.016072156 | G86: =+F86*4/(3.1415*D86^2) -> -0.2273812 | H86: =10.643*140^(-1.85)*D86^(-4.87)*ABS(F86)^1.85*IF(F86<0,-1,1) -> -0.00019247922 | I86: =+H86*E86 -> -0.043115345 | J86: =+I86/F86 -> 2.6826111 | K86: =-I89/(J89*1.851) -> 2.744816e-05 | M86: =+F86+K86+L86 -> -0.016044708 | O86: =+D86 -> 0.3
C87: =C19 -> RQ | D87: =D19 -> 0.35 | E87: =E19 -> 224 | F87: =M70 -> 0.16166034 | G87: =+F87*4/(3.1415*D87^2) -> 1.6803136 | H87: =10.643*140^(-1.85)*D87^(-4.87)*ABS(F87)^1.85*IF(F87<0,-1,1) -> 0.0065017803 | I87: =+H87*E87 -> 1.4563988 | J87: =+I87/F87 -> 9.0090047 | K87: =-I89/(J89*1.851) -> 2.744816e-05 | M87: =+F87+K87+L87 -> 0.16168779 | O87: =+D87 -> 0.35
B88: =B20 -> I | C88: =C20 -> GQ | D88: =D20 -> 0.35 | E88: =E20 -> 336 | F88: =M71 -> -0.13156828 | G88: =+F88*4/(3.1415*D88^2) -> -1.3675337 | H88: =10.643*140^(-1.85)*D88^(-4.87)*ABS(F88)^1.85*IF(F88<0,-1,1) -> -0.0044416621 | I88: =+H88*E88 -> -1.4923985 | J88: =+I88/F88 -> 11.343148 | K88: =-I89/(J89*1.851) -> 2.744816e-05 | L88: =-K79 -> -7.1878285e-06 | M88: =+F88+K88+L88 -> -0.13154802 | O88: =+D88 -> 0.35
H89: SUMA | I89: =+SUM(I85:I88) -> -0.0015295129 | J89: =+SUM(J85:J88) -> 30.104643
A91: 6ta iteración | N91: SELECCIONADA
A92: =A7 -> CIRCUITO | C92: =C7 -> TRAMO | D92: =D7 -> DIAM.(m) | E92: =E7 -> LONG.(m) | F92: CAUDAL (m3/s) | G92: VELOC.(m/s) | H92: J (m/m) | I92: Hi(m) | J92: Hi/Qi | K92: CORRECCIÓN | M92: CAUDAL (m3/s) | O92: DIAM.(m)
A93: =A8 -> PROPIO | B93: =B8 -> COMUN | K93: PROPIA | L93: COMUN
A94: =A9 -> I | C94: =C9 -> AB | D94: =D9 -> 0.2 | E94: =E9 -> 224 | F94: =M77 -> 0.01890956 | G94: =+F94*4/(3.1415*D94^2) -> 0.60192773 | H94: =10.643*140^(-1.85)*D94^(-4.87)*ABS(F94)^1.85*IF(F94<0,-1,1) -> 0.0018731464 | I94: =+H94*E94 -> 0.4195848 | J94: =+I94/F94 -> 22.189031 | K94: =-I98/(J98*1.851) -> 9.6650325e-07 | M94: =+F94+K94+L94 -> 0.018910526 | O94: =+D94 -> 0.2
C95: =C10 -> RB | D95: =D10 -> 0.3 | E95: =E10 -> 336 | F95: =M78 -> -0.08541169 | G95: =+F95*4/(3.1415*D95^2) -> -1.2083639 | H95: =10.643*140^(-1.85)*D95^(-4.87)*ABS(F95)^1.85*IF(F95<0,-1,1) -> -0.0042311042 | I95: =+H95*E95 -> -1.421651 | J95: =+I95/F95 -> 16.644689 | K95: =-I98/(J98*1.851) -> 9.6650325e-07 | M95: =+F95+K95+L95 -> -0.085410724 | O95: =+D95 -> 0.3
B96: =B11 -> II | C96: =C11 -> RQ | D96: =D11 -> 0.35 | E96: =E11 -> 224 | F96: =M79 -> 0.031090517 | G96: =+F96*4/(3.1415*D96^2) -> 0.32315791 | H96: =10.643*140^(-1.85)*D96^(-4.87)*ABS(F96)^1.85*IF(F96<0,-1,1) -> 0.0003079481 | I96: =+H96*E96 -> 0.068980374 | J96: =+I96/F96 -> 2.218695 | K96: =-I98/(J98*1.851) -> 9.6650325e-07 | L96: =-K105 -> -2.7155185e-06 | M96: =+F96+K96+L96 -> 0.031088768 | O96: =+D96 -> 0.35
C97: =C12 -> QA | D97: =D12 -> 0.25 | E97: =E12 -> 336 | F97: =M80 -> 0.04209206 | G97: =+F97*4/(3.1415*D97^2) -> 0.85751769 | H97: =10.643*140^(-1.85)*D97^(-4.87)*ABS(F97)^1.85*IF(F97<0,-1,1) -> 0.0027767046 | I97: =+H97*E97 -> 0.93297275 | J97: =+I97/F97 -> 22.165053 | K97: =-I98/(J98*1.851) -> 9.6650325e-07 | M97: =+F97+K97+L97 -> 0.042093026 | O97: =+D97 -> 0.25
H98: SUMA | I98: =+SUM(I94:I97) -> -0.00011309589 | J98: =+SUM(J94:J97) -> 63.217468
A100: =A15 -> CIRCUITO | C100: =C15 -> TRAMO | D100: =D15 -> DIAM.(m) | E100: =E15 -> LONG.(m) | F100: CAUDAL (m3/s) | G100: VELOC.(m/s) | H100: J (m/m) | I100: Hi(m) | J100: Hi/Qi | K100: CORRECCIÓN | M100: CAUDAL (m3/s) | O100: DIAM.(m)
A101: =A16 -> PROPIO | B101: =B16 -> COMUN | K101: PROPIA | L101: COMUN
A102: =A17 -> II | C102: =C17 -> HR | D102: =D17 -> 0.25 | E102: =E17 -> 336 | F102: =M85 -> 0.011001542 | G102: =+F102*4/(3.1415*D102^2) -> 0.22412819 | H102: =10.643*140^(-1.85)*D102^(-4.87)*ABS(F102)^1.85*IF(F102<0,-1,1) -> 0.00023197888 | I102: =+H102*E102 -> 0.077944904 | J102: =+I102/F102 -> 7.0849071 | K102: =-I106/(J106*1.851) -> 2.7155185e-06 | M102: =+F102+K102+L102 -> 0.011004258 | O102: =+D102 -> 0.25
C103: =C18 -> GH | D103: =D18 -> 0.3 | E103: =E18 -> 224 | F103: =M86 -> -0.016044708 | G103: =+F103*4/(3.1415*D103^2) -> -0.22699288 | H103: =10.643*140^(-1.85)*D103^(-4.87)*ABS(F103)^1.85*IF(F103<0,-1,1) -> -0.00019187153 | I103: =+H103*E103 -> -0.042979223 | J103: =+I103/F103 -> 2.6787165 | K103: =-I106/(J106*1.851) -> 2.7155185e-06 | M103: =+F103+K103+L103 -> -0.016041992 | O103: =+D103 -> 0.3
C104: =C19 -> RQ | D104: =D19 -> 0.35 | E104: =E19 -> 224 | F104: =M87 -> 0.16168779 | G104: =+F104*4/(3.1415*D104^2) -> 1.6805989 | H104: =10.643*140^(-1.85)*D104^(-4.87)*ABS(F104)^1.85*IF(F104<0,-1,1) -> 0.0065038228 | I104: =+H104*E104 -> 1.4568563 | J104: =+I104/F104 -> 9.0103048 | K104: =-I106/(J106*1.851) -> 2.7155185e-06 | M104: =+F104+K104+L104 -> 0.16169051 | O104: =+D104 -> 0.35
B105: =B20 -> I | C105: =C20 -> GQ | D105: =D20 -> 0.35 | E105: =E20 -> 336 | F105: =M88 -> -0.13154802 | G105: =+F105*4/(3.1415*D105^2) -> -1.3673231 | H105: =10.643*140^(-1.85)*D105^(-4.87)*ABS(F105)^1.85*IF(F105<0,-1,1) -> -0.0044403969 | I105: =+H105*E105 -> -1.4919734 | J105: =+I105/F105 -> 11.341664 | K105: =-I106/(J106*1.851) -> 2.7155185e-06 | L105: =-K96 -> -9.6650325e-07 | M105: =+F105+K105+L105 -> -0.13154627 | O105: =+D105 -> 0.35
H106: SUMA | I106: =+SUM(I102:I105) -> -0.00015137376 | J106: =+SUM(J102:J105) -> 30.115592

Sheet Datos Inic
A1: 5- DATOS INICIALES
A2: MALLAS "I" Y "II"
A3: Cantidad de edificios | C3: =+'DATOS Y SISTEMA IMPULSIÓN RÍO'!B3*'DATOS Y SISTEMA IMPULSIÓN RÍO'!B4 -> 72 | D3: lotes | E3: =+C3/12 -> 6
A4: Caudal por edificios | C4: =+C5/C3 -> 2.1465278 | D4: l/s/lote | G4: 20
A5: Caudal medio diario= | C5: =+'DATOS Y SISTEMA IMPULSIÓN RÍO'!B17 -> 154.55 | D5: l/s = | K5: K1 = | L5: =+'DATOS Y SISTEMA IMPULSIÓN RÍO'!B20 -> 1.2
A6: Caudal maximo diario= | C6: =L5*C5 -> 185.46 | D6: l/s = | E6: =+(C6*3600*2)/(1000)+90 -> 1425.312 | F6: m3 por hora | G6: =E6/(PI()*(G4/2)^2) -> 4.536909 | J6: =+G7+0.3 -> 6.9621241 | K6: K2 = | L6: =+'DATOS Y SISTEMA IMPULSIÓN RÍO'!B21 -> 1.5
A7: Caudal maximo horario= | C7: =ROUND(L6*C6,3) -> 278.19 | D7: l/s = | E7: =+(C7*3600*2)/(1000)+90 -> 2092.968 | F7: m3 por hora | G7: =E7/(PI()*(G4/2)^2) -> 6.6621241
A8: Diferencia para cubrir solo hora pico = | E8: =+E7-E6 -> 667.656 | F8: m3 por hora | G8: =E8/(PI()*(G4/2)^2) -> 2.1252151 | H8: Altura de la base del tanque = | J8: =Presiones!J16 -> 10.46
A9: Por Zonas de Presión | M9: DG= | N9: =+$C$7-G16-G18 -> 0 | O9: =+$C$7-H16-H18 -> 0
A10: Anillo | B10: Tramo | C10: Long (m) | D10: Nº de lotes por tramo | E10: Qa (l/s) | F10: Qc (l/s) | G10: Qt (l/s) | H10: Qcorr (l/s) | I10: Diam recomendado (mm) | J10: Diam comercial (mm) | K10: Diam adop (mm) | L10: Diam (m) | M10: V (m/s) ≥ 0,6
A11: I | B11: AB | C11: =11+100+12+100+1 -> 224 | D11: 7 | E11: =D11*$C$4*$L$5*$L$6 -> 27.04625 | F11: 0 | G11: =+E11+F11 -> 27.04625 | H11: =+G11 -> 27.04625 | I11: =+SQRT((4*H11/1000)/(3.14*1.2))*1000 -> 169.44473 | J11: =+IF(I11<=200,200,IF(I11<=250,250,IF(I11<=300,300,IF(I11<=350,350,350)))) -> 200 | K11: 200 | L11: =+K11/1000 -> 0.2 | M11: =(H11/1000)/((PI()*(K11/1000)^2)/4) -> 0.86090888 | N11: =IF((M11<=0.6),"DISMINUIR EL DIAMETRO ADOPTADO"," ")
B12: RB | C12: =11+100+12+100+12+100+1 -> 336 | D12: 13 | E12: =D12*$C$4*$L$5*$L$6 -> 50.22875 | F12: =+G11 -> 27.04625 | G12: =+E12+F12 -> 77.275 | H12: =+G12 -> 77.275 | I12: =+SQRT((4*H12/1000)/(3.14*1.2))*1000 -> 286.41388 | J12: =+IF(I12<=200,200,IF(I12<=250,250,IF(I12<=300,300,IF(I12<=350,350,350)))) -> 300 | K12: 300 | L12: =+K12/1000 -> 0.3 | M12: =(H12/1000)/((PI()*(K12/1000)^2)/4) -> 1.0932176 | N12: =IF((M12<=0.6),"DISMINUIR EL DIAMETRO ADOPTADO"," ")
B13: RQ | C13: =11+100+12+100+1 -> 224 | D13: 6 | E13: =D13*$C$4*$L$5*$L$6 -> 23.1825 | F13: =+G12 -> 77.275 | G13: =+E13+F13 -> 100.4575 | H13: =+G13 -> 100.4575 | I13: =+SQRT((4*H13/1000)/(3.14*1.2))*1000 -> 326.56206 | J13: =+IF(I13<=200,200,IF(I13<=250,250,IF(I13<=300,300,IF(I13<=350,350,350)))) -> 350 | K13: 350 | L13: =+K13/1000 -> 0.35 | M13: =(H13/1000)/((PI()*(K13/1000)^2)/4) -> 1.0441344 | N13: =IF((M13<=0.6),"DISMINUIR EL DIAMETRO ADOPTADO"," ")
B14: QA | C14: =11+100+12+100+12+100+1 -> 336 | D14: 13 | E14: =D14*$C$4*$L$5*$L$6 -> 50.22875 | F14: 0 | G14: =+E14+F14 -> 50.22875 | H14: =+G14 -> 50.22875 | I14: =+SQRT((4*H14/1000)/(3.14*1.2))*1000 -> 230.91425 | J14: =+IF(I14<=200,200,IF(I14<=250,250,IF(I14<=300,300,IF(I14<=350,350,350)))) -> 250 | K14: 250 | L14: =+K14/1000 -> 0.25 | M14: =(H14/1000)/((PI()*(K14/1000)^2)/4) -> 1.0232517 | N14: =IF((M14<=0.6),"DISMINUIR EL DIAMETRO ADOPTADO"," ")
A15: II | B15: HR | C15: =+C14 -> 336 | D15: =+D18 -> 13 | E15: =D15*$C$4*$L$5*$L$6 -> 50.22875 | F15: 0 | G15: =+E15+F15 -> 50.22875 | H15: =+G15 -> 50.22875 | I15: =+SQRT((4*H15/1000)/(3.14*1.2))*1000 -> 230.91425 | J15: =+IF(I15<=200,200,IF(I15<=250,250,IF(I15<=300,300,IF(I15<=350,350,350)))) -> 250 | K15: 250 | L15: =+K15/1000 -> 0.25 | M15: =(H15/1000)/((PI()*(K15/1000)^2)/4) -> 1.0232517 | N15: =IF((M15<=0.6),"DISMINUIR EL DIAMETRO ADOPTADO"," ")
B16: GH | C16: =+C11 -> 224 | D16: 7 | E16: =D16*$C$4*$L$5*$L$6 -> 27.04625 | F16: =+G15 -> 50.22875 | G16: =+E16+F16 -> 77.275 | H16: =+G16+$N$9*0.5 -> 77.275 | I16: =+SQRT((4*H16/1000)/(3.14*1.2))*1000 -> 286.41388 | J16: =+IF(I16<=200,200,IF(I16<=250,250,IF(I16<=300,300,IF(I16<=350,350,350)))) -> 300 | K16: 300 | L16: =+K16/1000 -> 0.3 | M16: =(H16/1000)/((PI()*(K16/1000)^2)/4) -> 1.0932176 | N16: =IF((M16<=0.6),"DISMINUIR EL DIAMETRO ADOPTADO"," ")
B17: RQ | C17: =+C16 -> 224 | D17: 0 | E17: =D17*$C$4*$L$5*$L$6 -> 0 | F17: =+F13 -> 77.275 | G17: =+G13 -> 100.4575 | H17: =+H13 -> 100.4575 | I17: =+SQRT((4*H17/1000)/(3.14*1.2))*1000 -> 326.56206 | J17: =+IF(I17<=200,200,IF(I17<=250,250,IF(I17<=300,300,IF(I17<=350,350,350)))) -> 350 | K17: 350 | L17: =+K17/1000 -> 0.35 | M17: =(H17/1000)/((PI()*(K17/1000)^2)/4) -> 1.0441344 | N17: =IF((M17<=0.6),"DISMINUIR EL DIAMETRO ADOPTADO"," ")
B18: GQ | C18: =+C12 -> 336 | D18: 13 | E18: =D18*$C$4*$L$5*$L$6 -> 50.22875 | F18: =G13+G14 -> 150.68625 | G18: =+E18+F18 -> 200.915 | H18: =+G18-$N$9*0.5 -> 200.915 | I18: =+I13 -> 326.56206 | J18: =+IF(I18<=200,200,IF(I18<=250,250,IF(I18<=300,300,IF(I18<=350,350,350)))) -> 350 | K18: 350 | L18: =+K18/1000 -> 0.35 | M18: =(H18/1000)/((PI()*(K18/1000)^2)/4) -> 2.0882688 | N18: =IF((M18<=0.6),"DISMINUIR EL DIAMETRO ADOPTADO"," ")
D19: =SUM(D11:D18) -> 72 | E19: =ROUND(SUM(E11:E18),3) -> 278.19 | F19: =+F14+F11 -> 0 | G19: =+G14+G11 -> 77.275 | H19: =+H14+H11 -> 77.275 | K19: Tubos PBA
C20: =+C4*86400 -> 185460 | D20: =+IF(D19=C3,"Verifica","Revisar") -> Verifica | E20: =+IF(ROUND(E19=C7,3),"Verifica","Revisar") -> Verifica | F20: =+F16+F18 -> 200.915 | G20: =ROUND(G16+G18,3) -> 278.19 | H20: =ROUND(H16+H18,3) -> 278.19 | K20: Adop (mm)
C21: Ubicación del tanque | D21: =K16 -> 300 | G21: =+IF(G20=C7,"Verifica","Revisar") -> Verifica | H21: =+IF(H20=C7,"Verifica","Revisar") -> Verifica
H22: =0.8*H20 -> 222.552 | K22: 50
K23: 65
D24: =K18 -> 350 | E24: =K15 -> 250 | K24: 75
K25: 100
K26: 150
G27: =N16 | I27: =N14 | K27: 200
K28: 250
F29: =K17 -> 350 | K29: 300
D30: =K14 -> 250 | E30: =K12 -> 300 | K30: 350
D34: =K11 -> 200

Sheet Presiones
A1: 6- PRESIONES
A2: VERIFICACIÓN DE PRESIONES | M2: AUXILIAR
A3: ANILLO | B3: TRAMO | C3: DIAMETRO (m) | D3: LONGITUD (m) | E3: Qcorregido (m3/s) | F3: J (m/m) | G3: H (m) | H3: Cota Piez m | I3: Cota Terr m | J3: Carga Dispon mca | M3: Qcorregido (m3/s)
A5: I | B5: A | C5: ='Datos Inic'!L11 -> 0.2 | D5: ='Datos Inic'!C11 -> 224 | E5: =+M5 -> 0.018910526 | F5: =10.643*140^(-1.85)*C5^(-4.87)*ABS(E5)^1.85*IF(E5<0,-1,1) -> 0.0018733236 | G5: =+F5*D5 -> 0.41962448 | H5: =+H6+G5 -> 105.07007 | I5: 94 | J5: =+H5-I5 -> 11.070075 | L5: Copiar | M5: =+Caudales!M94 -> 0.018910526 | N5: Caudales
B6: B | H6: =+H7 -> 104.65045 | I6: 92 | J6: =+H6-I6 -> 12.65045 | M6: =+Caudales!M95 -> -0.085410724
B7: B | C7: ='Datos Inic'!L12 -> 0.3 | D7: ='Datos Inic'!C12 -> 336 | E7: =+M6 -> -0.085410724 | F7: =10.643*140^(-1.85)*C7^(-4.87)*ABS(E7)^1.85*IF(E7<0,-1,1) -> -0.0042310156 | G7: =+F7*D7 -> -1.4216213 | H7: =+H8+G7 -> 104.65045 | I7: =+I6 -> 92 | J7: =+H7-I7 -> 12.65045 | M7: =+Caudales!M96 -> 0.031088768
B8: R | H8: =+H9 -> 106.07207 | I8: 94 | J8: =+H8-I8 -> 12.072072 | M8: =+Caudales!M97 -> 0.042093026
B9: R | C9: ='Datos Inic'!L13 -> 0.35 | D9: ='Datos Inic'!C13 -> 224 | E9: =+M7 -> 0.031088768 | F9: =10.643*140^(-1.85)*C9^(-4.87)*ABS(E9)^1.85*IF(E9<0,-1,1) -> 0.00030791605 | G9: =+F9*D9 -> 0.068973195 | H9: =+H10+G9 -> 106.07207 | I9: =+I8 -> 94 | J9: =+H9-I9 -> 12.072072
B10: Q | H10: =+H11 -> 106.0031 | I10: 96 | J10: =+H10-I10 -> 10.003098
B11: Q | C11: ='Datos Inic'!L14 -> 0.25 | D11: ='Datos Inic'!C14 -> 336 | E11: =+M8 -> 0.042093026 | F11: =10.643*140^(-1.85)*C11^(-4.87)*ABS(E11)^1.85*IF(E11<0,-1,1) -> 0.0027768226 | G11: =+F11*D11 -> 0.93301238 | H11: =+H18 -> 106.0031 | I11: =+I10 -> 96 | J11: =+H11-I11 -> 10.003098
B12: A | H12: =+H11-G11 -> 105.07009 | I12: =+I5 -> 94 | J12: =+H12-I12 -> 11.070086 | K12: =+SUM(G5:G12) -> -1.1205901e-05
A13: II | B13: R | C13: ='Datos Inic'!L15 -> 0.25 | D13: ='Datos Inic'!C15 -> 336 | E13: =+M14 -> 0.011004258 | F13: =10.643*140^(-1.85)*C13^(-4.87)*ABS(E13)^1.85*IF(E13<0,-1,1) -> 0.00023208482 | G13: =+F13*D13 -> 0.0779805 | H13: =+H14+G13 -> 107.49501 | I13: =+I8 -> 94 | J13: =+H13-I13 -> 13.495015
B14: H | H14: =+H15 -> 107.41703 | I14: 95 | J14: =+H14-I14 -> 12.417034 | L14: Copiar | M14: =Caudales!M102 -> 0.011004258 | N14: Caudales
B15: H | C15: ='Datos Inic'!L16 -> 0.3 | D15: ='Datos Inic'!C16 -> 224 | E15: =+M15 -> -0.016041992 | F15: =10.643*140^(-1.85)*C15^(-4.87)*ABS(E15)^1.85*IF(E15<0,-1,1) -> -0.00019181146 | G15: =+F15*D15 -> -0.042965767 | H15: =+H16+G15 -> 107.41703 | I15: =+I14 -> 95 | J15: =+H15-I15 -> 12.417034 | M15: =Caudales!M103 -> -0.016041992
B16: G | H16: =+I16+J16 -> 107.46 | I16: 97 | J16: 10.46 | K16: Ubicación y base del Tanque | M16: =Caudales!M104 -> 0.16169051
B17: G | C17: ='Datos Inic'!L17 -> 0.35 | D17: ='Datos Inic'!C17 -> 224 | E17: =+M16 -> 0.16169051 | F17: =10.643*140^(-1.85)*C17^(-4.87)*ABS(E17)^1.85*IF(E17<0,-1,1) -> 0.0065040248 | G17: =+F17*D17 -> 1.4569016 | H17: =+H16 -> 107.46 | I17: =+I16 -> 97 | J17: =+H17-I17 -> 10.46 | M17: =Caudales!M105 -> -0.13154627
B18: Q | H18: =+H17-G17 -> 106.0031 | I18: =+I10 -> 96 | J18: =+H18-I18 -> 10.003098
B19: Q | C19: ='Datos Inic'!L18 -> 0.35 | D19: ='Datos Inic'!C18 -> 336 | E19: =+M17 -> -0.13154627 | F19: =10.643*140^(-1.85)*C19^(-4.87)*ABS(E19)^1.85*IF(E19<0,-1,1) -> -0.0044402877 | G19: =+F19*D19 -> -1.4919367 | H19: =+H18 -> 106.0031 | I19: =+I18 -> 96 | J19: =+H19-I19 -> 10.003098
B20: R | H20: =+H19-G19 -> 107.49504 | I20: =+I8 -> 94 | J20: =+H20-I20 -> 13.495035 | K20: =+SUM(G13:G20) -> -2.0358144e-05
B21: CORREGIR EN LA ITERACION SELECCIONADA | I21: MÁXIMO | J21: =+MAX(J5:J20) -> 13.495035
I22: MÍNIMO | J22: =+MIN(J5:J20) -> 10.003098 | K22: >=10
I23: Perdida= | J23: =+J21-J22 -> 3.4919367
I24: VERIFICACIÓN DE LA PRESION MÍNIMA PERMITIDA: | J24: =+IF(J22>=10,"VERIFICA","NO VERIFICA") -> VERIFICA
D26: Ubicación del tanque
D27: =I16 -> 97 | G27: =I14 -> 95
D33: =I10 -> 96 | G33: =I8 -> 94
D39: =I5 -> 94 | G39: =I6 -> 92

Sheet RED CLOACAL
A1: 7- RED CLOACAL
A3: DESAGUE CLOACAL
A4: Valores adoptados para el cálculo
A5: Caudal por edificios | B5: ='Datos Inic'!C4 -> 2.1465278 | C5: l/s/lote
A6: Coeficiente de retorno (80 a 90%) | B6: 80 | C6: %
A7: K1 = | B7: ='Datos Inic'!L5 -> 1.2
A8: K2 = | B8: ='Datos Inic'!L6 -> 1.5
A9: Longitud total de la red | B9: =+SUM(C24:C98) -> 4084 | C9: m
A10: Caudal maximo por edificios | B10: =+B5*B6/100*B7*B8 -> 3.091 | C10: l/s/lote
A11: Tasa de infiltración | B11: 0.05 | C11: l/s/km
A12: Caudal máximo | B12: =(F94+E94)/1000 -> 0.2351202 | C12: m3/s
B13: =B12*1000 -> 235.1202 | C13: l/s
A14: Velocidad minima | B14: 0.6 | C14: m/s
A15: Velocidad máxima | B15: 5 | C15: m/s
A16: Formula de Bazin | B16: v=(87/(1+(γ/(√RH)))*(√RH*I)
A17: RH | B17: Radio hidráulico
A18: Valor del coeficiente γ, | B18: 0.22
A19: Coeficiente de escurrimiento | B19: 0.95
A20: PROFUNDIDAD DEL TUBO DEL REGISTRO MAS ALEJADO | B20: =1.2+R24 -> 1.45 | C20: m
A21: http://www.bvsde.paho.org/tecapro/documentos/sanea/169esp-diseno-alcantar.pdf
A23: Tramo | B23: Nº de lotes | C23: Longitud del tramo (m) | D23: Caudal del tramo (l/s) | E23: Caudal acumulado (l/s) | F23: Caudal de inflitración (l/s) | G23: Caudal mìnima (l/s) | H23: Pend. minima (%) | I23: Pend. adoptada (%) | J23: Descenso de tubería (m) | K23: Cota del Terreno sobre Registro a Entrada al Tramo | L23: Cota del Terreno sobre Registro a Salida del Tramo | M23: Cota de Fondo del Registro a Entrada al Tramo | N23: Cota de Fondo del Registro a Salida del Tramo | O23: Profundidad del Registro de Entrada (m) | P23: Prof. Min: 1,2 m | Q23: Profundidad del Registro de Salida (m) | R23: Diámetro de Tubería requerido (m) | S23: Radio Hidráulico (RH) | T23: Velocidad (m/seg) | U23: V.min.: 0,6 m/s | V23: V. max.: 5 m/s | W23: Caudal que podrá conducir (m3/s) | X23: Caudal obtenido a traves el área de escurrimiento (m3/s) | Y23: Verificación de caudales
A24: T7-6 | B24: 2 | C24: 112 | D24: =B24*$B$10 -> 6.182 | E24: =+D24 -> 6.182 | F24: =+$B$11*C24/1000 -> 0.0056 | G24: =+IF((E24+F24)>1.5,(E24+F24),1.5) -> 6.1876 | H24: =(0.0055*(G24^-0.47))*100 -> 0.23353245 | I24: 0.5 | J24: =C24*(I24/100) -> 0.56 | K24: 97 | L24: =+K25 -> 96.666667 | M24: =+K24-$B$20 -> 95.55 | N24: =+M24-J24 -> 94.99 | O24: =K24-M24 -> 1.45 | P24: =IF((K24-M24)>=1.2,"verifica","aumentar pendiente") -> verifica | Q24: =L24-N24 -> 1.6766667 | R24: 0.25 | S24: =R24/4 -> 0.0625 | T24: =(87/(1+(0.14/S24^(1/2))))*(S24*(I24/100))^(1/2) -> 0.98587003 | U24: =IF(T24>=$B$14,"verifica", "aumentar diámetro") -> verifica | V24: =IF(T24<=$B$15,"verifica","disminuir pend.") -> verifica | W24: =(3.14*(R24/2)^2*T24) -> 0.048369248 | X24: =(E24+F24)/1000 -> 0.0061876 | Y24: =IF(W24>=X24,"verifica","no verifica") -> verifica
A25: T6-5 | B25: 2 | C25: 112 | D25: =B25*$B$10 -> 6.182 | E25: =+E24+D25 -> 12.364 | F25: =+$B$11*C25/1000+F24 -> 0.0112 | G25: =+IF((E25+F25)>1.5,(E25+F25),1.5) -> 12.3752 | H25: =(0.0055*(G25^-0.47))*100 -> 0.16860216 | I25: 0.5 | J25: =C25*(I25/100) -> 0.56 | K25: =K24-(K24-K27)/(C24*3)*C24 -> 96.666667 | L25: =+K26 -> 96.333333 | M25: =+N24 -> 94.99 | N25: =+M25-J25 -> 94.43 | O25: =K25-M25 -> 1.6766667 | P25: =IF((K25-M25)>=1.2,"verifica","aumentar pendiente") -> verifica | Q25: =L25-N25 -> 1.9033333 | R25: 0.25 | S25: =R25/4 -> 0.0625 | T25: =(87/(1+(0.14/S25^(1/2))))*(S25*(I25/100))^(1/2) -> 0.98587003 | U25: =IF(T25>=$B$14,"verifica", "aumentar diámetro") -> verifica | V25: =IF(T25<=$B$15,"verifica","disminuir pend.") -> verifica | W25: =(3.14*(R25/2)^2*T25) -> 0.048369248 | X25: =(E25+F25)/1000 -> 0.0123752 | Y25: =IF(W25>=X25,"verifica","no verifica") -> verifica
A26: T5-4 | B26: 2 | C26: 112 | D26: =B26*$B$10 -> 6.182 | E26: =+E25+D26 -> 18.546 | F26: =+$B$11*C26/1000+F25 -> 0.0168 | G26: =+IF((E26+F26)>1.5,(E26+F26),1.5) -> 18.5628 | H26: =(0.0055*(G26^-0.47))*100 -> 0.13934784 | I26: 0.5 | J26: =C26*(I26/100) -> 0.56 | K26: =K24-(K24-K27)/(C24*3)*C24*2 -> 96.333333 | L26: =+K27 -> 96 | M26: =+N25 -> 94.43 | N26: =+M26-J26 -> 93.87 | O26: =K26-M26 -> 1.9033333 | P26: =IF((K26-M26)>=1.2,"verifica","aumentar pendiente") -> verifica | Q26: =L26-N26 -> 2.13 | R26: 0.25 | S26: =R26/4 -> 0.0625 | T26: =(87/(1+(0.14/S26^(1/2))))*(S26*(I26/100))^(1/2) -> 0.98587003 | U26: =IF(T26>=$B$14,"verifica", "aumentar diámetro") -> verifica | V26: =IF(T26<=$B$15,"verifica","disminuir pend.") -> verifica | W26: =(3.14*(R26/2)^2*T26) -> 0.048369248 | X26: =(E26+F26)/1000 -> 0.0185628 | Y26: =IF(W26>=X26,"verifica","no verifica") -> verifica
A27: T4-3 | B27: 2 | C27: 112 | D27: =B27*$B$10 -> 6.182 | E27: =+E26+D27 -> 24.728 | F27: =+$B$11*C27/1000+F25 -> 0.0168 | G27: =+IF((E27+F27)>1.5,(E27+F27),1.5) -> 24.7448 | H27: =(0.0055*(G27^-0.47))*100 -> 0.12173774 | I27: 0.5 | J27: =C27*(I27/100) -> 0.56 | K27: 96 | L27: =+K28 -> 95.333333 | M27: =+N26 -> 93.87 | N27: =+M27-J27 -> 93.31 | O27: =K27-M27 -> 2.13 | P27: =IF((K27-M27)>=1.2,"verifica","aumentar pendiente") -> verifica | Q27: =L27-N27 -> 2.0233333 | R27: 0.25 | S27: =R27/4 -> 0.0625 | T27: =(87/(1+(0.14/S27^(1/2))))*(S27*(I27/100))^(1/2) -> 0.98587003 | U27: =IF(T27>=$B$14,"verifica", "aumentar diámetro") -> verifica | V27: =IF(T27<=$B$15,"verifica","disminuir pend.") -> verifica | W27: =(3.14*(R27/2)^2*T27) -> 0.048369248 | X27: =(E27+F27)/1000 -> 0.0247448 | Y27: =IF(W27>=X27,"verifica","no verifica") -> verifica
A28: T3-2 | B28: 2 | C28: 112 | D28: =B28*$B$10 -> 6.182 | E28: =+E27+D28 -> 30.91 | F28: =+$B$11*C28/1000+F26 -> 0.0224 | G28: =+IF((E28+F28)>1.5,(E28+F28),1.5) -> 30.9324 | H28: =(0.0055*(G28^-0.47))*100 -> 0.10961457 | I28: 0.5 | J28: =C28*(I28/100) -> 0.56 | K28: =K27-(K27-K30)/(C28*3)*C24 -> 95.333333 | L28: =+K29 -> 94.666667 | M28: =+N27 -> 93.31 | N28: =+M28-J28 -> 92.75 | O28: =K28-M28 -> 2.0233333 | P28: =IF((K28-M28)>=1.2,"verifica","aumentar pendiente") -> verifica | Q28: =L28-N28 -> 1.9166667 | R28: 0.25 | S28: =R28/4 -> 0.0625 | T28: =(87/(1+(0.14/S28^(1/2))))*(S28*(I28/100))^(1/2) -> 0.98587003 | U28: =IF(T28>=$B$14,"verifica", "aumentar diámetro") -> verifica | V28: =IF(T28<=$B$15,"verifica","disminuir pend.") -> verifica | W28: =(3.14*(R28/2)^2*T28) -> 0.048369248 | X28: =(E28+F28)/1000 -> 0.0309324 | Y28: =IF(W28>=X28,"verifica","no verifica") -> verifica
A29: T2-1 | B29: 2 | C29: 112 | D29: =B29*$B$10 -> 6.182 | E29: =+E28+D29 -> 37.092 | F29: =+$B$11*C29/1000+F27 -> 0.0224 | G29: =+IF((E29+F29)>1.5,(E29+F29),1.5) -> 37.1144 | H29: =(0.0055*(G29^-0.47))*100 -> 0.10061848 | I29: 0.5 | J29: =C29*(I29/100) -> 0.56 | K29: =K28-(K27-K30)/(C29*3)*C28 -> 94.666667 | L29: =+K30 -> 94 | M29: =+N28 -> 92.75 | N29: =+M29-J29 -> 92.19 | O29: =K29-M29 -> 1.9166667 | P29: =IF((K29-M29)>=1.2,"verifica","aumentar pendiente") -> verifica | Q29: =L29-N29 -> 1.81 | R29: 0.25 | S29: =R29/4 -> 0.0625 | T29: =(87/(1+(0.14/S29^(1/2))))*(S29*(I29/100))^(1/2) -> 0.98587003 | U29: =IF(T29>=$B$14,"verifica", "aumentar diámetro") -> verifica | V29: =IF(T29<=$B$15,"verifica","disminuir pend.") -> verifica | W29: =(3.14*(R29/2)^2*T29) -> 0.048369248 | X29: =(E29+F29)/1000 -> 0.0371144 | Y29: =IF(W29>=X29,"verifica","no verifica") -> verifica
A30: T1-11 | B30: 1 | C30: 112 | D30: =B30*$B$10 -> 3.091 | E30: =+E29+D30 -> 40.183 | F30: =+$B$11*C30/1000+F29 -> 0.028 | G30: =+IF((E30+F30)>1.5,(E30+F30),1.5) -> 40.211 | H30: =(0.0055*(G30^-0.47))*100 -> 0.096899291 | I30: 0.5 | J30: =C30*(I30/100) -> 0.56 | K30: 94 | L30: =+K31 -> 93 | M30: =+N29 -> 92.19 | N30: =+M30-J30 -> 91.63 | O30: =K30-M30 -> 1.81 | P30: =IF((K30-M30)>=1.2,"verifica","aumentar pendiente") -> verifica | Q30: =L30-N30 -> 1.37 | R30: 0.25 | S30: =R30/4 -> 0.0625 | T30: =(87/(1+(0.14/S30^(1/2))))*(S30*(I30/100))^(1/2) -> 0.98587003 | U30: =IF(T30>=$B$14,"verifica", "aumentar diámetro") -> verifica | V30: =IF(T30<=$B$15,"verifica","disminuir pend.") -> verifica | W30: =(3.14*(R30/2)^2*T30) -> 0.048369248 | X30: =(E30+F30)/1000 -> 0.040211 | Y30: =IF(W30>=X30,"verifica","no verifica") -> verifica
A31: 11 | K31: =+(K30+K89)/2 -> 93 | M31: =+N30 -> 91.63 | O31: =K31-M31 -> 1.37
A35: T7-17 | B35: 1 | C35: 112 | D35: =B35*$B$10 -> 3.091 | E35: =+D35 -> 3.091 | F35: =+$B$11*C35/1000 -> 0.0056 | G35: =+IF((E35+F35)>1.5,(E35+F35),1.5) -> 3.0966 | H35: =(0.0055*(G35^-0.47))*100 -> 0.32333051 | I35: 0.7 | J35: =C35*(I35/100) -> 0.784 | K35: =+K24 -> 97 | L35: =+K36 -> 96 | M35: =+K35-$B$20 -> 95.55 | N35: =+M35-J35 -> 94.766 | O35: =K35-M35 -> 1.45 | P35: =IF((K35-M35)>=1.2,"verifica","aumentar pendiente") -> verifica | Q35: =L35-N35 -> 1.234 | R35: 0.15 | S35: =R35/4 -> 0.0375 | T35: =(87/(1+(0.14/S35^(1/2))))*(S35*(I35/100))^(1/2) -> 0.81810584 | U35: =IF(T35>=$B$14,"verifica", "aumentar diámetro") -> verifica | V35: =IF(T35<=$B$15,"verifica","disminuir pend.") -> verifica | W35: =(3.14*(R35/2)^2*T35) -> 0.014449794 | X35: =(E35+F35)/1000 -> 0.0030966 | Y35: =IF(W35>=X35,"verifica","no verifica") -> verifica
A36: 17 | K36: =+(K35+K83)/2 -> 96 | M36: =+N35 -> 94.766 | O36: =K36-M36 -> 1.234 | P36: =IF((K36-M36)>=1.2,"verifica","aumentar pendiente") -> verifica
A38: T6-16 | B38: 2 | C38: 112 | D38: =B38*$B$10 -> 6.182 | E38: =+D38 -> 6.182 | F38: =+$B$11*C38/1000 -> 0.0056 | G38: =+IF((E38+F38)>1.5,(E38+F38),1.5) -> 6.1876 | H38: =(0.0055*(G38^-0.47))*100 -> 0.23353245 | I38: 0.7 | J38: =C38*(I38/100) -> 0.784 | K38: =+K25 -> 96.666667 | L38: =+K39 -> 95.666667 | M38: =+K38-$B$20 -> 95.216667 | N38: =+M38-J38 -> 94.432667 | O38: =K38-M38 -> 1.45 | P38: =IF((K38-M38)>=1.2,"verifica","aumentar pendiente") -> verifica | Q38: =L38-N38 -> 1.234 | R38: 0.15 | S38: =R38/4 -> 0.0375 | T38: =(87/(1+(0.14/S38^(1/2))))*(S38*(I38/100))^(1/2) -> 0.81810584 | U38: =IF(T38>=$B$14,"verifica", "aumentar diámetro") -> verifica | V38: =IF(T38<=$B$15,"verifica","disminuir pend.") -> verifica | W38: =(3.14*(R38/2)^2*T38) -> 0.014449794 | X38: =(E38+F38)/1000 -> 0.0061876 | Y38: =IF(W38>=X38,"verifica","no verifica") -> verifica
A39: 16 | K39: =+(K25+K84)/2 -> 95.666667 | M39: =+N38 -> 94.432667 | O39: =K39-M39 -> 1.234 | P39: =IF((K39-M39)>=1.2,"verifica","aumentar pendiente") -> verifica
A41: T5-15 | B41: 2 | C41: 112 | D41: =B41*$B$10 -> 6.182 | E41: =+D41 -> 6.182 | F41: =+$B$11*C41/1000 -> 0.0056 | G41: =+IF((E41+F41)>1.5,(E41+F41),1.5) -> 6.1876 | H41: =(0.0055*(G41^-0.47))*100 -> 0.23353245 | I41: 0.7 | J41: =C41*(I41/100) -> 0.784 | K41: =+K26 -> 96.333333 | L41: =+K42 -> 95.388889 | M41: =+K41-$B$20 -> 94.883333 | N41: =+M41-J41 -> 94.099333 | O41: =K41-M41 -> 1.45 | P41: =IF((K41-M41)>=1.2,"verifica","aumentar pendiente") -> verifica | Q41: =L41-N41 -> 1.2895556 | R41: 0.15 | S41: =R41/4 -> 0.0375 | T41: =(87/(1+(0.14/S41^(1/2))))*(S41*(I41/100))^(1/2) -> 0.81810584 | U41: =IF(T41>=$B$14,"verifica", "aumentar diámetro") -> verifica | V41: =IF(T41<=$B$15,"verifica","disminuir pend.") -> verifica | W41: =(3.14*(R41/2)^2*T41) -> 0.014449794 | X41: =(E41+F41)/1000 -> 0.0061876 | Y41: =IF(W41>=X41,"verifica","no verifica") -> verifica
A42: 15 | K42: =+(K26+K85)/2 -> 95.388889 | M42: =+N41 -> 94.099333 | O42: =K42-M42 -> 1.2895556 | P42: =IF((K42-M42)>=1.2,"verifica","aumentar pendiente") -> verifica
A44: T4-14 | B44: 2 | C44: 112 | D44: =B44*$B$10 -> 6.182 | E44: =+D44 -> 6.182 | F44: =+$B$11*C44/1000 -> 0.0056 | G44: =+IF((E44+F44)>1.5,(E44+F44),1.5) -> 6.1876 | H44: =(0.0055*(G44^-0.47))*100 -> 0.23353245 | I44: 0.7 | J44: =C44*(I44/100) -> 0.784 | K44: =+K27 -> 96 | L44: =+K45 -> 95 | M44: =+K44-$B$20 -> 94.55 | N44: =+M44-J44 -> 93.766 | O44: =K44-M44 -> 1.45 | P44: =IF((K44-M44)>=1.2,"verifica","aumentar pendiente") -> verifica | Q44: =L44-N44 -> 1.234 | R44: 0.15 | S44: =R44/4 -> 0.0375 | T44: =(87/(1+(0.14/S44^(1/2))))*(S44*(I44/100))^(1/2) -> 0.81810584 | U44: =IF(T44>=$B$14,"verifica", "aumentar diámetro") -> verifica | V44: =IF(T44<=$B$15,"verifica","disminuir pend.") -> verifica | W44: =(3.14*(R44/2)^2*T44) -> 0.014449794 | X44: =(E44+F44)/1000 -> 0.0061876 | Y44: =IF(W44>=X44,"verifica","no verifica") -> verifica
A45: 14 | K45: =+(K27+K86)/2 -> 95 | M45: =+N44 -> 93.766 | O45: =K45-M45 -> 1.234 | P45: =IF((K45-M45)>=1.2,"verifica","aumentar pendiente") -> verifica
A47: T3-13 | B47: 2 | C47: 112 | D47: =B47*$B$10 -> 6.182 | E47: =+D47 -> 6.182 | F47: =+$B$11*C47/1000 -> 0.0056 | G47: =+IF((E47+F47)>1.5,(E47+F47),1.5) -> 6.1876 | H47: =(0.0055*(G47^-0.47))*100 -> 0.23353245 | I47: 2 | J47: =C47*(I47/100) -> 2.24 | K47: =+K28 -> 95.333333 | L47: =+K48 -> 93.333333 | M47: =+K47-$B$20 -> 93.883333 | N47: =+M47-J47 -> 91.643333 | O47: =K47-M47 -> 1.45 | P47: =IF((K47-M47)>=1.2,"verifica","aumentar pendiente") -> verifica | Q47: =L47-N47 -> 1.69 | R47: 0.1 | S47: =R47/4 -> 0.025 | T47: =(87/(1+(0.14/S47^(1/2))))*(S47*(I47/100))^(1/2) -> 1.0317918 | U47: =IF(T47>=$B$14,"verifica", "aumentar diámetro") -> verifica | V47: =IF(T47<=$B$15,"verifica","disminuir pend.") -> verifica | W47: =(3.14*(R47/2)^2*T47) -> 0.0080995654 | X47: =(E47+F47)/1000 -> 0.0061876 | Y47: =IF(W47>=X47,"verifica","no verifica") -> verifica
A48: 13 | K48: =+K87 -> 93.333333 | M48: =+N47 -> 91.643333 | O48: =K48-M48 -> 1.69 | P48: =IF((K48-M48)>=1.2,"verifica","aumentar pendiente") -> verifica
A50: T2-12 | B50: 2 | C50: 112 | D50: =B50*$B$10 -> 6.182 | E50: =+D50 -> 6.182 | F50: =+$B$11*C50/1000 -> 0.0056 | G50: =+IF((E50+F50)>1.5,(E50+F50),1.5) -> 6.1876 | H50: =(0.0055*(G50^-0.47))*100 -> 0.23353245 | I50: 2 | J50: =C50*(I50/100) -> 2.24 | K50: =+K29 -> 94.666667 | L50: =+K51 -> 92.888889 | M50: =+K50-$B$20 -> 93.216667 | N50: =+M50-J50 -> 90.976667 | O50: =K50-M50 -> 1.45 | P50: =IF((K50-M50)>=1.2,"verifica","aumentar pendiente") -> verifica | Q50: =L50-N50 -> 1.9122222 | R50: 0.1 | S50: =R50/4 -> 0.025 | T50: =(87/(1+(0.14/S50^(1/2))))*(S50*(I50/100))^(1/2) -> 1.0317918 | U50: =IF(T50>=$B$14,"verifica", "aumentar diámetro") -> verifica | V50: =IF(T50<=$B$15,"verifica","disminuir pend.") -> verifica | W50: =(3.14*(R50/2)^2*T50) -> 0.0080995654 | X50: =(E50+F50)/1000 -> 0.0061876 | Y50: =IF(W50>=X50,"verifica","no verifica") -> verifica
A51: 12 | K51: =+K88 -> 92.888889 | M51: =+N50 -> 90.976667 | O51: =K51-M51 -> 1.9122222 | P51: =IF((K51-M51)>=1.2,"verifica","aumentar pendiente") -> verifica
A53: T17-16 | B53: 4 | C53: 112 | D53: =B53*$B$10 -> 12.364 | E53: =+D53+G35 -> 15.4606 | F53: =+$B$11*C53/1000 -> 0.0056 | G53: =+IF((E53+F53)>1.5,(E53+F53),1.5) -> 15.4662 | H53: =(0.0055*(G53^-0.47))*100 -> 0.15182818 | I53: 0.5 | J53: =C53*(I53/100) -> 0.56 | K53: =+K36 -> 96 | L53: =+K54 -> 95.796296 | M53: =+K53-$B$20 -> 94.55 | N53: =+M53-J53 -> 93.99 | O53: =K53-M53 -> 1.45 | P53: =IF((K53-M53)>=1.2,"verifica","aumentar pendiente") -> verifica | Q53: =L53-N53 -> 1.8062963 | R53: 0.25 | S53: =R53/4 -> 0.0625 | T53: =(87/(1+(0.14/S53^(1/2))))*(S53*(I53/100))^(1/2) -> 0.98587003 | U53: =IF(T53>=$B$14,"verifica", "aumentar diámetro") -> verifica | V53: =IF(T53<=$B$15,"verifica","disminuir pend.") -> verifica | W53: =(3.14*(R53/2)^2*T53) -> 0.048369248 | X53: =(E53+F53)/1000 -> 0.0154662 | Y53: =IF(W53>=X53,"verifica","no verifica") -> verifica
A54: T16-15 | B54: 4 | C54: 112 | D54: =B54*$B$10 -> 12.364 | E54: =+D54+E53+G38 -> 34.0122 | F54: =+$B$11*C54/1000+F53+F44 -> 0.0168 | G54: =+IF((E54+F54)>1.5,(E54+F54),1.5) -> 34.029 | H54: =(0.0055*(G54^-0.47))*100 -> 0.10480779 | I54: 0.5 | J54: =C54*(I54/100) -> 0.56 | K54: =K53-(K53-K56)/(C53*3)*C53 -> 95.796296 | L54: =+K55 -> 95.660494 | M54: =+N53 -> 93.99 | N54: =+M54-J54 -> 93.43 | O54: =K54-M54 -> 1.8062963 | P54: =IF((K54-M54)>=1.2,"verifica","aumentar pendiente") -> verifica | Q54: =L54-N54 -> 2.2304938 | R54: 0.25 | S54: =R54/4 -> 0.0625 | T54: =(87/(1+(0.14/S54^(1/2))))*(S54*(I54/100))^(1/2) -> 0.98587003 | U54: =IF(T54>=$B$14,"verifica", "aumentar diámetro") -> verifica | V54: =IF(T54<=$B$15,"verifica","disminuir pend.") -> verifica | W54: =(3.14*(R54/2)^2*T54) -> 0.048369248 | X54: =(E54+F54)/1000 -> 0.034029 | Y54: =IF(W54>=X54,"verifica","no verifica") -> verifica
A55: T15-14 | B55: 4 | C55: 112 | D55: =B55*$B$10 -> 12.364 | E55: =+D55+E54+G41 -> 52.5638 | F55: =+$B$11*C55/1000+F54+G41 -> 6.21 | G55: =+IF((E55+F55)>1.5,(E55+F55),1.5) -> 58.7738 | H55: =(0.0055*(G55^-0.47))*100 -> 0.081067414 | I55: 0.5 | J55: =C55*(I55/100) -> 0.56 | K55: =K54-(K54-K56)/(C54*3)*C54 -> 95.660494 | L55: =+K56 -> 95.388889 | M55: =+N54 -> 93.43 | N55: =+M55-J55 -> 92.87 | O55: =K55-M55 -> 2.2304938 | P55: =IF((K55-M55)>=1.2,"verifica","aumentar pendiente") -> verifica | Q55: =L55-N55 -> 2.5188889 | R55: 0.3 | S55: =R55/4 -> 0.075 | T55: =(87/(1+(0.14/S55^(1/2))))*(S55*(I55/100))^(1/2) -> 1.1148353 | U55: =IF(T55>=$B$14,"verifica", "aumentar diámetro") -> verifica | V55: =IF(T55<=$B$15,"verifica","disminuir pend.") -> verifica | W55: =(3.14*(R55/2)^2*T55) -> 0.078763116 | X55: =(E55+F55)/1000 -> 0.0587738 | Y55: =IF(W55>=X55,"verifica","no verifica") -> verifica
A56: T14-13 | B56: 4 | C56: 112 | D56: =B56*$B$10 -> 12.364 | E56: =+D56+E55+G44 -> 71.1154 | F56: =+$B$11*C56/1000+F54+G44 -> 6.21 | G56: =+IF((E56+F56)>1.5,(E56+F56),1.5) -> 77.3254 | H56: =(0.0055*(G56^-0.47))*100 -> 0.071260894 | I56: 0.5 | J56: =C56*(I56/100) -> 0.56 | K56: =+K42 -> 95.388889 | L56: =+K57 -> 94.592593 | M56: =+N55 -> 92.87 | N56: =+M56-J56 -> 92.31 | O56: =K56-M56 -> 2.5188889 | P56: =IF((K56-M56)>=1.2,"verifica","aumentar pendiente") -> verifica | Q56: =L56-N56 -> 2.2825926 | R56: 0.3 | S56: =R56/4 -> 0.075 | T56: =(87/(1+(0.14/S56^(1/2))))*(S56*(I56/100))^(1/2) -> 1.1148353 | U56: =IF(T56>=$B$14,"verifica", "aumentar diámetro") -> verifica | V56: =IF(T56<=$B$15,"verifica","disminuir pend.") -> verifica | W56: =(3.14*(R56/2)^2*T56) -> 0.078763116 | X56: =(E56+F56)/1000 -> 0.0773254 | Y56: =IF(W56>=X56,"verifica","no verifica") -> verifica
A57: T13-12 | B57: 4 | C57: 112 | D57: =B57*$B$10 -> 12.364 | E57: =+D57+E56+G47 -> 89.667 | F57: =+$B$11*C57/1000+F56+G50 -> 12.4032 | G57: =+IF((E57+F57)>1.5,(E57+F57),1.5) -> 102.0702 | H57: =(0.0055*(G57^-0.47))*100 -> 0.062543211 | I57: 0.5 | J57: =C57*(I57/100) -> 0.56 | K57: =K56-(K56-K59)/(C56*3)*C56 -> 94.592593 | L57: =+K58 -> 94.061728 | M57: =+N56 -> 92.31 | N57: =+M57-J57 -> 91.75 | O57: =K57-M57 -> 2.2825926 | P57: =IF((K57-M57)>=1.2,"verifica","aumentar pendiente") -> verifica | Q57: =L57-N57 -> 2.3117284 | R57: 0.35 | S57: =R57/4 -> 0.0875 | T57: =(87/(1+(0.14/S57^(1/2))))*(S57*(I57/100))^(1/2) -> 1.235154 | U57: =IF(T57>=$B$14,"verifica", "aumentar diámetro") -> verifica | V57: =IF(T57<=$B$15,"verifica","disminuir pend.") -> verifica | W57: =(3.14*(R57/2)^2*T57) -> 0.1187755 | X57: =(E57+F57)/1000 -> 0.1020702 | Y57: =IF(W57>=X57,"verifica","no verifica") -> verifica
A58: T12-11 | B58: 4 | C58: 112 | D58: =B58*$B$10 -> 12.364 | E58: =+D58+E57+G50 -> 108.2186 | F58: =+$B$11*C58/1000+F57+F51 -> 12.4088 | G58: =+IF((E58+F58)>1.5,(E58+F58),1.5) -> 120.6274 | H58: =(0.0055*(G58^-0.47))*100 -> 0.057820665 | I58: 1 | J58: =C58*(I58/100) -> 1.12 | K58: =K57-(K57-K59)/(C57*3)*C57 -> 94.061728 | L58: =+K59 -> 93 | M58: =+N57 -> 91.75 | N58: =+M58-J58 -> 90.63 | O58: =K58-M58 -> 2.3117284 | P58: =IF((K58-M58)>=1.2,"verifica","aumentar pendiente") -> verifica | Q58: =L58-N58 -> 2.37 | R58: 0.35 | S58: =R58/4 -> 0.0875 | T58: =(87/(1+(0.14/S58^(1/2))))*(S58*(I58/100))^(1/2) -> 1.7467715 | U58: =IF(T58>=$B$14,"verifica", "aumentar diámetro") -> verifica | V58: =IF(T58<=$B$15,"verifica","disminuir pend.") -> verifica | W58: =(3.14*(R58/2)^2*T58) -> 0.16797392 | X58: =(E58+F58)/1000 -> 0.1206274 | Y58: =IF(W58>=X58,"verifica","no verifica") -> verifica
A59: 11 | K59: =+K31 -> 93 | M59: =+N58 -> 90.63 | O59: =K59-M59 -> 2.37 | P59: =IF((K59-M59)>=1.2,"verifica","aumentar pendiente") -> verifica
A63: T17-27 | B63: 1 | C63: 112 | D63: =B63*$B$10 -> 3.091 | E63: =+D63 -> 3.091 | F63: =+$B$11*C63/1000 -> 0.0056 | G63: =+IF((E63+F63)>1.5,(E63+F63),1.5) -> 3.0966 | H63: =(0.0055*(G63^-0.47))*100 -> 0.32333051 | I63: 0.7 | J63: =C63*(I63/100) -> 0.784 | K63: =+K36 -> 96 | L63: =+K64 -> 95.5 | M63: =+K63-$B$20 -> 94.55 | N63: =+M63-J63 -> 93.766 | O63: =K63-M63 -> 1.45 | P63: =IF((K63-M63)>=1.2,"verifica","aumentar pendiente") -> verifica | Q63: =L63-N63 -> 1.734 | R63: 0.15 | S63: =R63/4 -> 0.0375 | T63: =(87/(1+(0.14/S63^(1/2))))*(S63*(I63/100))^(1/2) -> 0.81810584 | U63: =IF(T63>=$B$14,"verifica", "aumentar diámetro") -> verifica | V63: =IF(T63<=$B$15,"verifica","disminuir pend.") -> verifica | W63: =(3.14*(R63/2)^2*T63) -> 0.014449794 | X63: =(E63+F63)/1000 -> 0.0030966 | Y63: =IF(W63>=X63,"verifica","no verifica") -> verifica
A64: 27 | K64: =+(K63+K83)/2 -> 95.5 | M64: =+N63 -> 93.766 | O64: =K64-M64 -> 1.734 | P64: =IF((K64-M64)>=1.2,"verifica","aumentar pendiente") -> verifica
A66: T16-26 | B66: 2 | C66: 112 | D66: =B66*$B$10 -> 6.182 | E66: =+D66 -> 6.182 | F66: =+$B$11*C66/1000 -> 0.0056 | G66: =+IF((E66+F66)>1.5,(E66+F66),1.5) -> 6.1876 | H66: =(0.0055*(G66^-0.47))*100 -> 0.23353245 | I66: 0.7 | J66: =C66*(I66/100) -> 0.784 | K66: =+K54 -> 95.796296 | L66: =+K67 -> 95.231481 | M66: =+K66-$B$20 -> 94.346296 | N66: =+M66-J66 -> 93.562296 | O66: =K66-M66 -> 1.45 | P66: =IF((K66-M66)>=1.2,"verifica","aumentar pendiente") -> verifica | Q66: =L66-N66 -> 1.6691852 | R66: 0.15 | S66: =R66/4 -> 0.0375 | T66: =(87/(1+(0.14/S66^(1/2))))*(S66*(I66/100))^(1/2) -> 0.81810584 | U66: =IF(T66>=$B$14,"verifica", "aumentar diámetro") -> verifica | V66: =IF(T66<=$B$15,"verifica","disminuir pend.") -> verifica | W66: =(3.14*(R66/2)^2*T66) -> 0.014449794 | X66: =(E66+F66)/1000 -> 0.0061876 | Y66: =IF(W66>=X66,"verifica","no verifica") -> verifica
A67: 26 | K67: =+(K54+K84)/2 -> 95.231481 | M67: =+N66 -> 93.562296 | O67: =K67-M67 -> 1.6691852 | P67: =IF((K67-M67)>=1.2,"verifica","aumentar pendiente") -> verifica
A69: T15-25 | B69: 2 | C69: 112 | D69: =B69*$B$10 -> 6.182 | E69: =+D69 -> 6.182 | F69: =+$B$11*C69/1000 -> 0.0056 | G69: =+IF((E69+F69)>1.5,(E69+F69),1.5) -> 6.1876 | H69: =(0.0055*(G69^-0.47))*100 -> 0.23353245 | I69: 0.7 | J69: =C69*(I69/100) -> 0.784 | K69: =+K55 -> 95.660494 | L69: =+K70 -> 95.052469 | M69: =+K69-$B$20 -> 94.210494 | N69: =+M69-J69 -> 93.426494 | O69: =K69-M69 -> 1.45 | P69: =IF((K69-M69)>=1.2,"verifica","aumentar pendiente") -> verifica | Q69: =L69-N69 -> 1.6259753 | R69: 0.15 | S69: =R69/4 -> 0.0375 | T69: =(87/(1+(0.14/S69^(1/2))))*(S69*(I69/100))^(1/2) -> 0.81810584 | U69: =IF(T69>=$B$14,"verifica", "aumentar diámetro") -> verifica | V69: =IF(T69<=$B$15,"verifica","disminuir pend.") -> verifica | W69: =(3.14*(R69/2)^2*T69) -> 0.014449794 | X69: =(E69+F69)/1000 -> 0.0061876 | Y69: =IF(W69>=X69,"verifica","no verifica") -> verifica
A70: 25 | K70: =+(K55+K85)/2 -> 95.052469 | M70: =+N69 -> 93.426494 | O70: =K70-M70 -> 1.6259753 | P70: =IF((K70-M70)>=1.2,"verifica","aumentar pendiente") -> verifica
A72: T14-24 | B72: 2 | C72: 112 | D72: =B72*$B$10 -> 6.182 | E72: =+D72 -> 6.182 | F72: =+$B$11*C72/1000 -> 0.0056 | G72: =+IF((E72+F72)>1.5,(E72+F72),1.5) -> 6.1876 | H72: =(0.0055*(G72^-0.47))*100 -> 0.23353245 | I72: 0.7 | J72: =C72*(I72/100) -> 0.784 | K72: =+K56 -> 95.388889 | L72: =+K73 -> 94.694444 | M72: =+K72-$B$20 -> 93.938889 | N72: =+M72-J72 -> 93.154889 | O72: =K72-M72 -> 1.45 | P72: =IF((K72-M72)>=1.2,"verifica","aumentar pendiente") -> verifica | Q72: =L72-N72 -> 1.5395556 | R72: 0.15 | S72: =R72/4 -> 0.0375 | T72: =(87/(1+(0.14/S72^(1/2))))*(S72*(I72/100))^(1/2) -> 0.81810584 | U72: =IF(T72>=$B$14,"verifica", "aumentar diámetro") -> verifica | V72: =IF(T72<=$B$15,"verifica","disminuir pend.") -> verifica | W72: =(3.14*(R72/2)^2*T72) -> 0.014449794 | X72: =(E72+F72)/1000 -> 0.0061876 | Y72: =IF(W72>=X72,"verifica","no verifica") -> verifica
A73: 24 | K73: =+(K56+K86)/2 -> 94.694444 | M73: =+N72 -> 93.154889 | O73: =K73-M73 -> 1.5395556 | P73: =IF((K73-M73)>=1.2,"verifica","aumentar pendiente") -> verifica
A75: T13-23 | B75: 2 | C75: 112 | D75: =B75*$B$10 -> 6.182 | E75: =+D75 -> 6.182 | F75: =+$B$11*C75/1000 -> 0.0056 | G75: =+IF((E75+F75)>1.5,(E75+F75),1.5) -> 6.1876 | H75: =(0.0055*(G75^-0.47))*100 -> 0.23353245 | I75: 2 | J75: =C75*(I75/100) -> 2.24 | K75: =+K57 -> 94.592593 | L75: =+K76 -> 93.333333 | M75: =+K75-$B$20 -> 93.142593 | N75: =+M75-J75 -> 90.902593 | O75: =K75-M75 -> 1.45 | P75: =IF((K75-M75)>=1.2,"verifica","aumentar pendiente") -> verifica | Q75: =L75-N75 -> 2.4307407 | R75: 0.15 | S75: =R75/4 -> 0.0375 | T75: =(87/(1+(0.14/S75^(1/2))))*(S75*(I75/100))^(1/2) -> 1.3828513 | U75: =IF(T75>=$B$14,"verifica", "aumentar diámetro") -> verifica | V75: =IF(T75<=$B$15,"verifica","disminuir pend.") -> verifica | W75: =(3.14*(R75/2)^2*T75) -> 0.024424611 | X75: =(E75+F75)/1000 -> 0.0061876 | Y75: =IF(W75>=X75,"verifica","no verifica") -> verifica
A76: 23 | K76: =+K87 -> 93.333333 | M76: =+N75 -> 90.902593 | O76: =K76-M76 -> 2.4307407 | P76: =IF((K76-M76)>=1.2,"verifica","aumentar pendiente") -> verifica
A78: T12-22 | B78: 2 | C78: 112 | D78: =B78*$B$10 -> 6.182 | E78: =+D78 -> 6.182 | F78: =+$B$11*C78/1000 -> 0.0056 | G78: =+IF((E78+F78)>1.5,(E78+F78),1.5) -> 6.1876 | H78: =(0.0055*(G78^-0.47))*100 -> 0.23353245 | I78: 2 | J78: =C78*(I78/100) -> 2.24 | K78: =+K58 -> 94.061728 | L78: =+K79 -> 92.888889 | M78: =+K78-$B$20 -> 92.611728 | N78: =+M78-J78 -> 90.371728 | O78: =K78-M78 -> 1.45 | P78: =IF((K78-M78)>=1.2,"verifica","aumentar pendiente") -> verifica | Q78: =L78-N78 -> 2.5171605 | R78: 0.15 | S78: =R78/4 -> 0.0375 | T78: =(87/(1+(0.14/S78^(1/2))))*(S78*(I78/100))^(1/2) -> 1.3828513 | U78: =IF(T78>=$B$14,"verifica", "aumentar diámetro") -> verifica | V78: =IF(T78<=$B$15,"verifica","disminuir pend.") -> verifica | W78: =(3.14*(R78/2)^2*T78) -> 0.024424611 | X78: =(E78+F78)/1000 -> 0.0061876 | Y78: =IF(W78>=X78,"verifica","no verifica") -> verifica
A79: 22 | K79: =K88+K119 -> 92.888889 | M79: =+N78 -> 90.371728 | O79: =K79-M79 -> 2.5171605 | P79: =IF((K79-M79)>=1.2,"verifica","aumentar pendiente") -> verifica
A83: T27-26 | B83: 2 | C83: 112 | D83: =B83*$B$10 -> 6.182 | E83: =+D83+G63 -> 9.2786 | F83: =+$B$11*C83/1000 -> 0.0056 | G83: =+IF((E83+F83)>1.5,(E83+F83),1.5) -> 9.2842 | H83: =(0.0055*(G83^-0.47))*100 -> 0.19298466 | I83: 0.5 | J83: =C83*(I83/100) -> 0.56 | K83: 95 | L83: =+K84 -> 94.666667 | M83: =+K83-$B$20 -> 93.55 | N83: =+M83-J83 -> 92.99 | O83: =K83-M83 -> 1.45 | P83: =IF((K83-M83)>=1.2,"verifica","aumentar pendiente") -> verifica | Q83: =L83-N83 -> 1.6766667 | R83: 0.15 | S83: =R83/4 -> 0.0375 | T83: =(87/(1+(0.14/S83^(1/2))))*(S83*(I83/100))^(1/2) -> 0.69142563 | U83: =IF(T83>=$B$14,"verifica", "aumentar diámetro") -> verifica | V83: =IF(T83<=$B$15,"verifica","disminuir pend.") -> verifica | W83: =(3.14*(R83/2)^2*T83) -> 0.012212305 | X83: =(E83+F83)/1000 -> 0.0092842 | Y83: =IF(W83>=X83,"verifica","no verifica") -> verifica
A84: T26-25 | B84: 2 | C84: 112 | D84: =B84*$B$10 -> 6.182 | E84: =+D84+E83+G66 -> 21.6482 | F84: =+$B$11*C84/1000+F83 -> 0.0112 | G84: =+IF((E84+F84)>1.5,(E84+F84),1.5) -> 21.6594 | H84: =(0.0055*(G84^-0.47))*100 -> 0.12960115 | I84: 0.5 | J84: =C84*(I84/100) -> 0.56 | K84: =K83-(K83-K86)/(C83*3)*C83 -> 94.666667 | L84: =+K85 -> 94.444444 | M84: =+N83 -> 92.99 | N84: =+M84-J84 -> 92.43 | O84: =K84-M84 -> 1.6766667 | P84: =IF((K84-M84)>=1.2,"verifica","aumentar pendiente") -> verifica | Q84: =L84-N84 -> 2.0144444 | R84: 0.3 | S84: =R84/4 -> 0.075 | T84: =(87/(1+(0.14/S84^(1/2))))*(S84*(I84/100))^(1/2) -> 1.1148353 | U84: =IF(T84>=$B$14,"verifica", "aumentar diámetro") -> verifica | V84: =IF(T84<=$B$15,"verifica","disminuir pend.") -> verifica | W84: =(3.14*(R84/2)^2*T84) -> 0.078763116 | X84: =(E84+F84)/1000 -> 0.0216594 | Y84: =IF(W84>=X84,"verifica","no verifica") -> verifica
A85: T25-24 | B85: 2 | C85: 112 | D85: =B85*$B$10 -> 6.182 | E85: =+D85+E84+G69 -> 34.0178 | F85: =+$B$11*C85/1000+F84 -> 0.0168 | G85: =+IF((E85+F85)>1.5,(E85+F85),1.5) -> 34.0346 | H85: =(0.0055*(G85^-0.47))*100 -> 0.10479969 | I85: 0.5 | J85: =C85*(I85/100) -> 0.56 | K85: =K84-(K84-K86)/(C84*3)*C84 -> 94.444444 | L85: =+K86 -> 94 | M85: =+N84 -> 92.43 | N85: =+M85-J85 -> 91.87 | O85: =K85-M85 -> 2.0144444 | P85: =IF((K85-M85)>=1.2,"verifica","aumentar pendiente") -> verifica | Q85: =L85-N85 -> 2.13 | R85: 0.3 | S85: =R85/4 -> 0.075 | T85: =(87/(1+(0.14/S85^(1/2))))*(S85*(I85/100))^(1/2) -> 1.1148353 | U85: =IF(T85>=$B$14,"verifica", "aumentar diámetro") -> verifica | V85: =IF(T85<=$B$15,"verifica","disminuir pend.") -> verifica | W85: =(3.14*(R85/2)^2*T85) -> 0.078763116 | X85: =(E85+F85)/1000 -> 0.0340346 | Y85: =IF(W85>=X85,"verifica","no verifica") -> verifica
A86: T24-23 | B86: 2 | C86: 112 | D86: =B86*$B$10 -> 6.182 | E86: =+D86+E85+G72 -> 46.3874 | F86: =+$B$11*C86/1000+F85 -> 0.0224 | G86: =+IF((E86+F86)>1.5,(E86+F86),1.5) -> 46.4098 | H86: =(0.0055*(G86^-0.47))*100 -> 0.090584967 | I86: 0.5 | J86: =C86*(I86/100) -> 0.56 | K86: 94 | L86: =+K87 -> 93.333333 | M86: =+N85 -> 91.87 | N86: =+M86-J86 -> 91.31 | O86: =K86-M86 -> 2.13 | P86: =IF((K86-M86)>=1.2,"verifica","aumentar pendiente") -> verifica | Q86: =L86-N86 -> 2.0233333 | R86: 0.3 | S86: =R86/4 -> 0.075 | T86: =(87/(1+(0.14/S86^(1/2))))*(S86*(I86/100))^(1/2) -> 1.1148353 | U86: =IF(T86>=$B$14,"verifica", "aumentar diámetro") -> verifica | V86: =IF(T86<=$B$15,"verifica","disminuir pend.") -> verifica | W86: =(3.14*(R86/2)^2*T86) -> 0.078763116 | X86: =(E86+F86)/1000 -> 0.0464098 | Y86: =IF(W86>=X86,"verifica","no verifica") -> verifica
A87: T23-22 | B87: 2 | C87: 112 | D87: =B87*$B$10 -> 6.182 | E87: =+D87+E86+G75 -> 58.757 | F87: =+$B$11*C87/1000+F86 -> 0.028 | G87: =+IF((E87+F87)>1.5,(E87+F87),1.5) -> 58.785 | H87: =(0.0055*(G87^-0.47))*100 -> 0.081060154 | I87: 0.5 | J87: =C87*(I87/100) -> 0.56 | K87: =K86-(K86-K89)/(C86*3)*C86 -> 93.333333 | L87: =+K88 -> 92.888889 | M87: =+N86 -> 91.31 | N87: =+M87-J87 -> 90.75 | O87: =K87-M87 -> 2.0233333 | P87: =IF((K87-M87)>=1.2,"verifica","aumentar pendiente") -> verifica | Q87: =L87-N87 -> 2.1388889 | R87: 0.3 | S87: =R87/4 -> 0.075 | T87: =(87/(1+(0.14/S87^(1/2))))*(S87*(I87/100))^(1/2) -> 1.1148353 | U87: =IF(T87>=$B$14,"verifica", "aumentar diámetro") -> verifica | V87: =IF(T87<=$B$15,"verifica","disminuir pend.") -> verifica | W87: =(3.14*(R87/2)^2*T87) -> 0.078763116 | X87: =(E87+F87)/1000 -> 0.058785 | Y87: =IF(W87>=X87,"verifica","no verifica") -> verifica
A88: T22-21 | B88: 2 | C88: 112 | D88: =B88*$B$10 -> 6.182 | E88: =+D88+E87+G78 -> 71.1266 | F88: =+$B$11*C88/1000+F87 -> 0.0336 | G88: =+IF((E88+F88)>1.5,(E88+F88),1.5) -> 71.1602 | H88: =(0.0055*(G88^-0.47))*100 -> 0.074098808 | I88: 0.5 | J88: =C88*(I88/100) -> 0.56 | K88: =K87-(K87-K89)/(C87*3)*C87 -> 92.888889 | L88: =+K89 -> 92 | M88: =+N87 -> 90.75 | N88: =+M88-J88 -> 90.19 | O88: =K88-M88 -> 2.1388889 | P88: =IF((K88-M88)>=1.2,"verifica","aumentar pendiente") -> verifica | Q88: =L88-N88 -> 1.81 | R88: 0.3 | S88: =R88/4 -> 0.075 | T88: =(87/(1+(0.14/S88^(1/2))))*(S88*(I88/100))^(1/2) -> 1.1148353 | U88: =IF(T88>=$B$14,"verifica", "aumentar diámetro") -> verifica | V88: =IF(T88<=$B$15,"verifica","disminuir pend.") -> verifica | W88: =(3.14*(R88/2)^2*T88) -> 0.078763116 | X88: =(E88+F88)/1000 -> 0.0711602 | Y88: =IF(W88>=X88,"verifica","no verifica") -> verifica
A89: 21 | K89: 92 | M89: =+N88 -> 90.19 | O89: =K89-M89 -> 1.81 | P89: =IF((K89-M89)>=1.2,"verifica","aumentar pendiente") -> verifica
A91: T11-21 | B91: 1 | C91: 112 | D91: =B91*$B$10 -> 3.091 | E91: =+D91+G30+G58 -> 163.9294 | F91: =+$B$11*C91/1000 -> 0.0056 | G91: =+IF((E91+F91)>1.5,(E91+F91),1.5) -> 163.935 | H91: =(0.0055*(G91^-0.47))*100 -> 0.050057251 | I91: 1 | J91: =C91*(I91/100) -> 1.12 | K91: =+K59 -> 93 | L91: =+K92 -> 92 | M91: =+K91-$B$20 -> 91.55 | N91: =+M91-J91 -> 90.43 | O91: =K91-M91 -> 1.45 | P91: =IF((K91-M91)>=1.2,"verifica","aumentar pendiente") -> verifica | Q91: =L91-N91 -> 1.57 | R91: 0.35 | S91: =R91/4 -> 0.0875 | T91: =(87/(1+(0.14/S91^(1/2))))*(S91*(I91/100))^(1/2) -> 1.7467715 | U91: =IF(T91>=$B$14,"verifica", "aumentar diámetro") -> verifica | V91: =IF(T91<=$B$15,"verifica","disminuir pend.") -> verifica | W91: =(3.14*(R91/2)^2*T91) -> 0.16797392 | X91: =(E91+F91)/1000 -> 0.163935 | Y91: =IF(W91>=X91,"verifica","no verifica") -> verifica
A92: 21 | K92: =+K89 -> 92 | M92: =+N91 -> 90.43 | O92: =K92-M92 -> 1.57 | P92: =IF((K92-M92)>=1.2,"verifica","aumentar pendiente") -> verifica
A94: T21-PTAR | B94: 0 | C94: 500 | D94: =B94*$B$10 -> 0 | E94: =+D94+G88+G91 -> 235.0952 | F94: =$B$11*C94/1000 -> 0.025 | G94: =+IF((E94+F94)>1.5,(E94+F94),1.5) -> 235.1202 | H94: =(0.0055*(G94^-0.47))*100 -> 0.04225289 | I94: 4 | J94: =C94*(I94/100) -> 20 | K94: =+K89 -> 92 | L94: =+K95 -> 73 | M94: =+K94-$B$20 -> 90.55 | N94: =+M94-J94 -> 70.55 | O94: =K94-M94 -> 1.45 | P94: =IF((K94-M94)>=1.2,"verifica","aumentar pendiente") -> verifica | Q94: =L94-N94 -> 2.45 | R94: 0.5 | S94: =R94/4 -> 0.125 | T94: =(87/(1+(0.14/S94^(1/2))))*(S94*(I94/100))^(1/2) -> 4.4068181 | U94: =IF(T94>=$B$14,"verifica", "aumentar diámetro") -> verifica | V94: =IF(T94<=$B$15,"verifica","disminuir pend.") -> verifica | W94: =(3.14*(R94/2)^2*T94) -> 0.86483805 | X94: =(E94+F94)/1000 -> 0.2351202 | Y94: =IF(W94>=X94,"verifica","no verifica") -> verifica
A95: PTAR | K95: 73 | M95: =+N94 -> 70.55 | O95: =K95-M95 -> 2.45 | P95: =IF((K95-M95)>=1.2,"verifica","aumentar pendiente") -> verifica
A97: Nº de lotes totales | B97: =SUM(B24:B96) -> 72 | D97: =SUM(D24:D96) -> 222.552
A99: VERIFICACIÓN | B99: =+IF(B97='Datos Inic'!D19,"OK","No") -> OK | E99: =+IF(ROUNDUP(D97,3)=(ROUNDUP((0.8*'Datos Inic'!C7),3)),"OK","No") -> OK

Sheet TRATAMIENTO PRELIMINAR
A1: 8- TRATAMIENTO PRELIMINAR
A3: Datos | B3: Valores | C3: Unidades
A4: Parametros de Cálculo
A5: Caudal Máximo | B5: ='RED CLOACAL'!G94/1000 -> 0.2351202 | C5: m3/s
A6: Caudal Medio | B6: =+B5/'RED CLOACAL'!B7/'RED CLOACAL'!B8 -> 0.13062233 | C6: m3/s
A7: Caudal Mínimo | B7: =+B6*0.5 -> 0.065311167 | C7: m3/s
A8: Caudal Máximo | B8: =+B5*1000 -> 235.1202 | C8: l/s
A9: Caudal Medio | B9: =+B6*1000 -> 130.62233 | C9: l/s
A10: Caudal Mínimo | B10: =+B7*1000 -> 65.311167 | C10: l/s
A12: Datos Constructivos
A13: Predimencsionado del ancho del canal
A14: - Con Q max. y velocidad de 0,3 m/s
A15: Se adopta un ancho de canal b = | B15: 2 | C15: m. | D15: Se prefiere más ancho que alto, se puede ir variando para obtener dimensiones constructivamente prácticas
A17: Cálculo de la lámina en el canal
A18: La altura de la lamina de agua en el tanque de arena resulta:
A19: - Para caudal maximo: H max = | B19: =+(((B5/0.3))/($B$15)) -> 0.391867 | C19: m.
A20: - Para caudal medio: H med.= | B20: =+(((B6/0.3))/($B$15)) -> 0.21770389 | C20: m.
A21: - Para caudal minimo: H min. = | B21: =+(((B7/0.3))/($B$15)) -> 0.10885194 | C21: m. | F21: Caudal (l/s) de Vertedores Parshall
A22: Inclinación de la reja | B22: 45 | C22: º | D22: 30 a 45° | F22: Altura H | G22: Ancho de la Garganta
A23: Grosor de las barras | B23: 0.3 | C23: cm | F23: (cm) | G23: 7,6 cm | H23: 15,2 cm | I23: 22,9 cm | J23: 30,5 cm
A24: Ancho de las barras | B24: 2.5 | C24: cm | F24: 3 | G24: 0.8 | H24: 1.4 | I24: 2.5 | J24: 3.1
A25: Esparcimiento entre barras | B25: 1 | C25: cm | F25: 4 | G25: 1.2 | H25: 2.3 | I25: 4 | J25: 4.6
A26: Velocidad de las aguas (0,40 a 0,75 m/s) | B26: 0.6 | C26: m/s | F26: 5 | G26: 1.5 | H26: 3.2 | I26: 5.5 | J26: 7
A27: Conclusiones sobre las rejas | F27: 6 | G27: 2.3 | H27: 4.5 | I27: 7.3 | J27: 9.9
A28: Area útil de las rejas | B28: =+B5/B26 -> 0.391867 | C28: m2 | F28: 7 | G28: 2.9 | H28: 5.7 | I28: 9.1 | J28: 12.5
A29: Eficiencia de las rejas | B29: =+B25/(B25+B23) -> 0.76923077 | F29: 8 | G29: 3.5 | H29: 7.1 | I29: 11.1 | J29: 14.5
A30: Sección de escurrimiento del canal | B30: =+B28/B29 -> 0.5094271 | C30: m2 | F30: 9 | G30: 4.3 | H30: 8.5 | I30: 13.5 | J30: 17.7
A31: Ancho del canal de rejas | B31: =+B30/(B19) -> 1.3 | C31: m | F31: 10 | G31: 5 | H31: 10.3 | I31: 15.8 | J31: 20.9
A32: Números de barras | B32: =+INT(B31/(B25/100+B23/100)) -> 100 | C32: un | F32: 11 | G32: 5.8 | H32: 11.6 | I32: 18.1 | J32: 23.8
A33: Pérdida de carga en las rejas | F33: 12 | G33: 6.7 | H33: 13.4 | I33: 21.2 | J33: 27.4
A34: Rejas limpias | B34: =1.43*(B26^2-(B26*B29)^2)/(2*9.81) -> 0.010712773 | C34: m | F34: 13 | G34: 7.5 | H34: 15.2 | I34: 23.8 | J34: 31
A35: Rejas 50% sucias | B35: =1.43*((2*B26)^2-(B26*B29)^2)/(2*9.81) -> 0.08942837 | C35: m | F35: 14 | G35: 8.5 | H35: 17.3 | I35: 26.6 | J35: 34.8
A36: Altura del agua antes de las rejas a 50% sucias | F36: 15 | G36: 9.4 | H36: 19.1 | I36: 29.2 | J36: 38.4
A37: Altura a caudal máximo | B37: =+$B$35+B19 -> 0.48129537 | C37: m | F37: 16 | G37: 10.8 | H37: 21.1 | I37: 32.4 | J37: 42.5
A38: Altura a caudal medio | B38: =+$B$35+B20 -> 0.30713226 | C38: m
A39: Altura a caudal mínimo | B39: =+$B$35+B21 -> 0.19828031 | C39: m
A40: Mantenimiento de la rejas
A41: Cantidad de material retenido (0,03 - 0,05 - 0,10) | B41: =+B68/1000 -> 0.05 | C41: l/m3/d
A42: Tiempo de limpieza | B42: 2 | C42: d
A43: Longitud del depósito previo a las rejas | B43: 2 | C43: m
A44: Profundidad del deposito previo de las rejas | B44: =+((B42*86400*B6*B41/1000)/(B43*B15)) -> 0.28214424 | C44: m
A46: DIMENSIONAMIENTO DEL DESARENADOR
A50: Verificación de las velocidades de agotamiento del canal de V = 0,3 m/s
A51: V = Qmax/S | B51: =B5/(B19*B15) -> 0.3 | C51: m/s
A52: V = Qmed/S | B52: =B6/(B20*B15) -> 0.3 | C52: m/s
A53: V = Qmin/S | B53: =B7/(B21*B15) -> 0.3 | C53: m/s
A55: Longitud del desarenador (L)
A56: Se estima 25 veces el tirante maximo:
A57: L = 25 x H max = | B57: =25*B19 -> 9.796675 | C57: m.
A58: Se adopta L = | B58: 9.4 | C58: m.
A60: Determinacion del Area Superficial (A): | F60: =+B15 -> 2
A61: A = L x b = | B61: =B58*B15 -> 18.8 | C61: m2.
E62: =+K108 -> 1.0625907
A63: Índice de Agotamiento superficial (T): | E63: =+B37 -> 0.48129537 | G63: =B20 -> 0.21770389 | H63: =B19 -> 0.391867
A64: Para Q med. debe estar entre 600 y 1.200 m3/m2.dia | G64: =B21 -> 0.10885194
A65: T = Q/A = | B65: =B6*86400/B61 -> 600.30689 | C65: m3/m2.dia
A66: 600 <= | B66: =+IF(B65<=1200,B65>=600) -> TRUE | C66: <=1200 | H66: =+B76 -> 0.21010741
A67: Cantidad de material retenido (mr)
A68: Cantidad de material retenido para 1000 m3/d de agua residual (30 - 50 - 100) = | B68: 50 | C68: litros
A69: mr = Qmed. x s/1000 = | B69: =B6*86400*B68/1000000 -> 0.56428848 | C69: m3/día
A72: Profundidad del deposito de arena
A73: Para remoción del material retenido cada = | B73: 7 | C73: días
A75: Volumen = | B75: =B69*B73 -> 3.9500194 | C75: m3
A76: hdeposito = | B76: =B75/B61 -> 0.21010741 | C76: m
A79: VERIFICACIÓN DEL DIMENSIONAMIENTO DE LAS REJAS
E80: DESARENADOR
A81: Cálculo del área útil | G81: =+B58 -> 9.4
A82: Admitiendose que para el caudal máximo la velocidad a travéz de las rejas
A83: sea de 0,60 m/s, se calcula el área útil.
A84: Au = Qmáx / vel. = | B84: =B5/0.6 -> 0.391867 | C84: m2
B85: =B6/0.6 -> 0.21770389 | C85: m2
B86: =B7/0.6 -> 0.10885194 | C86: m2
A88: Cálculo del área total (S)
A89: Considerar que las rejas tendrán barras de sección rectangular
A90: 10 x 40 mm, y separación de 10 a 25 mm.
A91: a = | B91: 10 | C91: mm
A92: t = | B92: 3 | C92: mm
A93: Cálculo de la eficiencia: E = a / a + t = | B93: =B91/(B91+B92) -> 0.76923077
A94: S = Au / E = | B94: =B84/B93 -> 0.5094271 | C94: m2
B95: =B85/B93 -> 0.28301506 | C95: m2
B96: =B86/B93 -> 0.14150753 | C96: m2 | F96: =+B15 -> 2
A98: Cálculo del ancho del canal (b)
A99: b = S / Hmáx. = | B99: =B94/B19 -> 1.3 | C99: m
A100: número de barras = | B100: 100 | C100: un
A101: Valor adoptado = | B101: =((B100+1)*B91+B100*B92)/1000 -> 1.31 | C101: m
B103: =+B94/B$101 -> 0.38887565 | C103: m
B104: =+B85/B$101 -> 0.16618617 | C104: m | M104: Relacción L/A = | N104: 0.889
B105: =+B86/B$101 -> 0.083093087 | C105: m | M105: Cantidades de losas = | N105: =+(M115-L109*2)/(M109) -> 4.2212554
G106: =+J107 -> 0.3
A107: Verificación de las velocidades (0,4 < V [0,6] < 0,75 m/s) | I107: =+J109 -> 0.53129537 | J107: 0.3
A108: V= Qmax/Au | B108: =B5/B94 -> 0.46153846 | C108: m/s | E108: REJAS | G108: =I107 -> 0.53129537 | K108: =+J109*2 -> 1.0625907
A109: V= Qmed/Au | B109: =B6/B95 -> 0.46153846 | C109: m/s | H109: =+B37 -> 0.48129537 | J109: =H109+0.05 -> 0.53129537 | L109: 0.015 | M109: =F96/N104-L109*2 -> 2.2197188 | P109: =+B19 -> 0.391867
A110: V= Qmin/Au | B110: =B7/B96 -> 0.46153846 | C110: m/s | E110: =+B32 -> 100 | H110: =+B44 -> 0.28214424
I111: =+G112 -> 2 | J111: =+((J109^2+I107^2)^0.5) -> 0.75136512 | K111: =B76 -> 0.21010741
A112: Cálculo de pérdida de carga | G112: =+B43 -> 2
A113: Para las rejas limpias | E113: =+B101 -> 1.31
A114: V = V´x E = | B114: =MAX(B108:B110)*B93 -> 0.35502959 | C114: m/s
A115: hf = 1,43 x (V´2 - V2)/ 2 x g = | B115: =1.43*((MAX(B108:B110))^2-B114^2)/19.62 -> 0.0063389192 | C115: m | J115: =+I111+I107+J107+0.3 -> 3.1312954 | M115: =+G81 -> 9.4
A116: Para rejas 50% sucias | L116: =+M115+J115 -> 12.531295
A117: V´= 2 x V' = | B117: 1.7 | C117: m/s | J117: REJAS | M117: DESARENADOR
...

Sheet LAGUNA FACULTATIVA
A1: 9- LAGUNA FACULTATIVA
A3: Datos | B3: Valores | C3: Unidades
A4: Parámetros
A5: Población de los departamentos = | B5: =+ 'DATOS Y SISTEMA IMPULSIÓN RÍO'!B11 -> 66528 | C5: hab
A6: Caudal unitario por persona por departamento = | B6: =+'DATOS Y SISTEMA IMPULSIÓN RÍO'!B13 -> 200 | C6: l/hab/d
A7: Personales de logística = | B7: =+'DATOS Y SISTEMA IMPULSIÓN RÍO'!B12 -> 950.4 | C7: funcionarios
A8: Caudal unitario por trabajadores de logisticas = | B8: =+'DATOS Y SISTEMA IMPULSIÓN RÍO'!B14 -> 50 | C8: l/hab/d
A9: K1 = | B9: =+'RED CLOACAL'!B7 -> 1.2
A10: K2 = | B10: =+'RED CLOACAL'!B8 -> 1.5
A11: Porcentaje de retorno = | B11: =+'RED CLOACAL'!B6 -> 80 | C11: %
A12: Caudal unitario de infiltración = | B12: =+'RED CLOACAL'!B11 -> 0.05 | C12: l/s/km
A13: Longitud de la tubería = | B13: =+SUM('RED CLOACAL'!C24:C95)+6+30 -> 4120 | C13: m
A14: Caudal unitario total = | B14: =(B6*B9*B10*B11/100*B5+B8*B9*B10*B11/100*B7)/(B5)+((B12/1000)*B13*86400/B5) -> 289.2961 | C14: l/hab/d
A15: Caudal medio diario = | B15: =+B14*B5/1000 -> 19246.291 | C15: m3 / d
A16: Caudal medio horario = | B16: =+B15/24 -> 801.9288 | C16: m3 / h
A17: Caudal medio horario = | B17: =+B16/3600*1000 -> 222.758 | C17: l / s
A18: DBO5 = | B18: =54/B14*1000 -> 186.65996 | C18: mg DBO5 / l
A19: Carga Orgánica horaria = | B19: =B18*B16/1000 -> 149.688 | C19: Kg DBO5 / h
A20: Carga Orgánica diaria = | B20: =+B18*B15/1000 -> 3592.512 | C20: Kg DBO5 / d
A21: Volumen de lodos anuales estimados = | B21: 0.6 | C21: m3 lodos.d/m3.año
A22: Periodo entre limpieza de lodos = | B22: 10 | C22: años
A23: Temperatura media promedio del mes más frio (en 30 años)
A24: Temp del aire = | B24: 12 | C24: ºC | D24: Fuente: weatherspark | F24: p/ Villa Florida | H24: https://es.weatherspark.com/y/29135/Clima-promedio-en-Villa-Florida-Paraguay-durante-todo-el-a%C3%B1o#:~:text=En%20Villa%20Florida%2C%20los%20veranos,m%C3%A1s%20de%2036%20%C2%B0C.
A25: Temp del agua = | B25: =+B24+1 -> 13 | C25: ºC
A26: Constante de depuración para Lag. Fac. en el mes más frio: k = | B26: 0.31 | C26: 1/d
A28: Radiación media del sol (según datos del IAN)
A29: Rsm = | B29: 50 | C29: %
A31: Carga orgánica diaria
A32: Números de lagunas paralelos = | B32: 1 | C32: Un.
A33: Cod por laguna = | B33: =+B20/B32 -> 3592.512 | C33: Kg.DBO/d
A35: Carga orgánica superficial máxima
A36: Cosm : para que no se torne anaeróbica
A37: Segun: | B37: Cosm
A38: Oswald : | B38: =0.196*(((123+(B29/100*(202-123)))*(1+0.00925*130))*((3.6+3.9)/2*0.96)) -> 252.53865 | C38: Kg.DBO/ha.d
A39: McGarry y Pescod : | B39: =400.6*1.0993^(B24-20) -> 187.83699 | C39: Kg.DBO/ha.d
A40: Yanes et al: | B40: =357.4*1.085^(B25-20) -> 201.90468 | C40: Kg.DBO/ha.d
A41: Sáenz: | B41: =250*1.0443^(B25-20) -> 184.57083 | C41: Kg.DBO/ha.d
A43: Adoptado: | B43: =B41 -> 184.57083 | C43: Kg.DBO/ha.d | D43: Sáenz
A45: Carga orgánica superficial aplicada
A46: Cos= 0,80 x Cosm = | B46: =0.8*B43 -> 147.65666 | C46: Kg.DBO/ha.d
A48: Cálculo del área promedio
A49: A= Cod/Cos= | B49: =+B33/B46*10000 -> 243301.72 | C49: m2
A51: Secciones medias de la laguna
A52: Relación: Lm/Bm= | B52: 2
A53: Lm= | B53: =+(B49*B52)^0.5 -> 697.56967 | C53: m
A54: Bm= | B54: =+B49/B53 -> 348.78483 | C54: m
A56: Profundidad adoptada
A57: h (1,50 a 2,50) = | B57: 2 | C57: m
A58: Altura para acumulación de lodos : Hc = | B58: =+B64/B49 -> 0.47462775 | C58: m
A59: Altura útil : 1,5 < Hu = | B59: =+B57+B58 -> 2.4746277 | C59: m
A60: Altura de ola : 0,5 < Ho = | B60: 0.49 | C60: m
A61: Altura total : Ht = | B61: =+B59+B60 -> 2.9646277 | C61: m
A63: Volumen de la laguna
A64: V para lodos = | B64: =+B15*B21*B22 -> 115477.75 | C64: m3.lodos
A65: V total = | B65: =+B49*B57+B64 -> 602081.19 | C65: m3
A67: Dimensiones varias
A68: Pendiente del talud mojado: 2 < x/y < 3 = | B68: 2
A69: Pendiente del talud seco: 1 < x/y < 2 = | B69: 1.5
A70: Largo terreno : Lt = | B70: =+B74+2*(B68*B61) -> 704.47892 | C70: m
A71: Ancho terreno : Bt = | B71: =+B75+2*(B68*B61) -> 355.69409 | C71: m
A72: Largo superior : Ls = | B72: =+(B59*B68)*2+B74 -> 702.51892 | C72: m
A73: Ancho superior : Bs = | B73: =+(B59*B68)*2+B75 -> 353.73409 | C73: m
A74: Largo inferior : Li = | B74: =+B53-(B59*B68) -> 692.62041 | C74: m
A75: Ancho inferior : Bi = | B75: =+B54-(B59*B68) -> 343.83558 | C75: m
A76: Altura del dique : Ad = | B76: 0.5 | C76: m
A77: Solera del dique : 3 < Sd = | B77: 3 | C77: m
A78: Base del dique : Bd = | B78: =+(B69*B76+B77+B68*B61) -> 9.6792555 | C78: m
A81: Tiempo de detención mínimo
A82: Tdmín= | B82: =3.5*1.085^(35-B25) -> 21.0631 | C82: d
A84: Cálculo del tiempo de detención
A85: Tdmín < Td inicial = V/Q = | B85: =+B65/B15 -> 31.282972 | C85: d
A86: Tdmín < Td al período de limpieza = (V - V lodos)/Q = | B86: =+(B65-B64)/B15 -> 25.282972 | C86: d
A88: Eficiencia esperada
A89: Ef : 70 a 95 %; Ef inicial = | B89: =+(1-1/(1+B26*B85))*100 -> 90.652215 | C89: %
A90: Ef : 70 a 95 %; Ef al período de limpieza = | B90: =+(1-1/(1+B26*B86))*100 -> 88.684866 | C90: %
A92: Parámetros del efluente (DBO < 50 mg/l)
A93: DBOinicio= | B93: =+(1-B89/100)*B18 -> 17.448572 | C93: mg DBO/l
A94: DBO al período de limpieza = | B94: =+(1-B90/100)*B18 -> 21.120825 | C94: mg DBO/l
A96: Parámetros de Coli termotolerantes (ColiT < 1000 UFC/100ml) | D96: Unidades formadoras coli termotolerantes por 100 ml
A97: Números de lagunas en serie = | B97: 1
A98: Coli termotolerantes = | B98: =(1-99/100)^B97*10000000 -> 100000 | C98: UFC/100ml | D98: Como no verifica se tiene que calcular el sistema de cloración
A101: Sistema de cloración
A102: Tiempo de contacto = | B102: 20 | C102: min | D102: de 15 a 30 min
B103: =+B102/60 -> 0.33333333 | C103: h
A104: Volumen de reservorio de contacto = | B104: =1.3*B16*B103 -> 347.50248 | C104: m³
A105: Relación largo/ancho = | B105: 2 | H105: =+B53 -> 697.56967
A106: Profundidad = | B106: 0.3 | C106: m
A107: Superficie = | B107: =+B104/B106 -> 1158.3416 | C107: m²
A108: Ancho = | B108: =(B107/B105)^0.5 -> 24.065968 | C108: m
A109: Largo = | B109: =+B108*2 -> 48.131935 | C109: m
A110: Dosis aproximada (Lagunas: 10 a Reactores: 60) = | B110: 30 | C110: ppm | E110: =+B54 -> 348.78483
A111: Consumo diario = | B111: =B15*1000*B110/1000000 -> 577.38874 | C111: Kg Cl2 | K111: =B75 -> 343.83558 | L111: =+B73 -> 353.73409 | M111: =+B71 -> 355.69409
A112: Consumo diario de Hipoclorito de Sodio (8%) = | B112: =+B111/0.08 -> 7217.3592 | C112: l/d
A113: Consumo mesual de Hipoclorito de Sodio (30% de reserva) = | B113: =B112*30*1.3 -> 281477.01 | C113: l/mes
A114: Relación de disolución (1/4) = | B114: 0.25
A115: Consumo diario de Hipoclorito de Sodio en disolución = | B115: =+B112/B114 -> 28869.437 | C115: L/d
A116: Consumo mensual de Hipoclorito de Sodio en disolución = | B116: =+B115*30 -> 866083.1 | C116: L/mes
A117: Consumo mensual de Hipoclorito de Sodio sin disolución = | B117: =+B116*B114 -> 216520.78 | C117: L/mes | H117: =+H131 -> 692.62041
A118: Tanque de disolucción = | B118: 220000 | C118: L
A119: Necesidad de cloro por cada tanque = | B119: =+B118*B114 -> 55000 | C119: L | H119: =+B72 -> 702.51892
...
